mlp_v1/v3_2/buffer.v
module buffer (   
        input clk, 
        input reset,

        input reset_mu_in,
        input done_in,
        input write_neuron_in,
        input [11:0] out_neuron_addr_in,

        output reg reset_mu_out,
        output reg done_out,
        output reg write_neuron_out,
        output reg [11:0] out_neuron_addr_out
    );

    always @(posedge clk) begin
        if (reset) begin
            reset_mu_out <= 0;
            done_out <= 0;
            write_neuron_out <= 0;
            out_neuron_addr_out <= 0;
        end else begin 
            reset_mu_out <= reset_mu_in;
            done_out <= done_in;
            write_neuron_out <= write_neuron_in;
            out_neuron_addr_out <= out_neuron_addr_in;
        end
    end
    
endmodule

mlp_v1/v3/softmax.v
module softmax(
        input clk, 
        input reset,
        input done,
        input [15:0] in, 
        output reg finished, 
        output reg [15:0] result
    );

    reg prev_done;

    always @(posedge clk) begin    
        prev_done <= done;

        if (reset) begin
            result <= 0;
            finished <= 0;
            prev_done <= 0;
        end else begin 
            if (done && ~prev_done) begin
                finished <= 1;
                result <= in;
            end else begin
                finished <= 0;
            end
        end
    end

endmodule

mlp_v1/negative_test_v2/relu.v
module relu 
    (   
        input wire signed [15:0] in,
        output reg signed [15:0] out
    );

    always @* begin
        if (in < 0)
            out = 0;
        else
            out = in;
    end

endmodule

mlp_v1/v3_2/multiply_unit.v
module multiply_unit 
    (   
        input wire clk,
        input wire reset,
        input wire signed [15:0] op1,
        input wire signed [7:0] op2,
        input wire signed [7:0] bias,
        output reg signed [15:0] out
    );

    reg signed [15:0] product;
    reg signed [15:0] sum;

    always @(posedge clk) begin
        product = op1 * op2;

        if (reset) begin
            sum = 0 + product;
        end else begin
            sum = sum + product;
        end

        out = sum + bias;
    end
    
endmodule


// what to do in case of overflows???

mlp_v1/v3/bias_mem.v
module bias_mem
    (
        input wire clk,
        input wire reset,
        input wire[15:0] input_addr,
        output reg signed [7:0] bias_val
    );

    wire [5:0] bias_addr = input_addr[15:10];

    // 3 * 16 + 1 (maximum number of possible output neurons)
    reg signed [7:0] bias_mem[0:48];

    initial begin 
        bias_mem[6'b000000] = 80;
        bias_mem[6'b000001] = -96;

        bias_mem[6'b010000] = -14;
        bias_mem[6'b010001] = 73;

        bias_mem[6'b100000] = 112;
    end

    always @(posedge clk) begin
        if (reset) begin
            bias_val <= 0;
        end else begin
            bias_val <= bias_mem[bias_addr];
        end
    end

endmodule

mlp_v1/v3/weight_mem.v
module weight_mem
    (
        input wire clk, 
        input wire reset,
        input wire [15:0] input_addr,
        output reg signed [7:0] weight_val
    );

    // 2^16 (size of neuron address) requires 65536 addresses
    reg signed [7:0] weight_mem[0:65535];

    // initializing input layer
    initial begin
        // layer 1 neuron 0 
        weight_mem[16'h0000] <= -3;
        weight_mem[16'h0001] <= 14;
        weight_mem[16'h0002] <= 3;
        weight_mem[16'h0003] <= -8;

        // layer 0 neuron 1
        weight_mem[16'h0400] <= 4;
        weight_mem[16'h0401] <= -6;
        weight_mem[16'h0402] <= 16;
        weight_mem[16'h0403] <= 8;

        // layer 1 neuron 0
        weight_mem[16'h4000] <= -4;
        weight_mem[16'h4001] <= -5;

        // layer 1 neuron 1
        weight_mem[16'h4400] <= 6;
        weight_mem[16'h4401] <= 2;

        // layer 2 neuron 0
        weight_mem[16'h8000] <= 3;
        weight_mem[16'h8001] <= 2;     
    end

    always @(posedge clk) begin
        if (reset) begin
            weight_val <= 0;
        end else begin 
            weight_val <= weight_mem[input_addr];
        end
    end

endmodule

mlp_v1/v3/neuron_mem.v
module neuron_mem
    (
        input wire clk, 
        input wire reset,
        input wire write_enable,
        input wire [11:0] input_addr,
        input wire signed [15:0] data,
        input wire [11:0] output_addr,
        output reg signed [15:0] neuron_val
    );

    // 2^12 (size of neuron address) requires 4096 addresses
    reg signed [15:0] neuron_mem[0:4095];

    // initializing input layer
    initial begin
        neuron_val <= 0;

        neuron_mem[0] <= 7;
        neuron_mem[1] <= 3;
        neuron_mem[2] <= -8;
        neuron_mem[3] <= 5;
    end

    always @(posedge clk) begin
        if (reset) begin
            neuron_val <= 0;
        end else begin 
            if (input_addr == output_addr && write_enable) begin
                neuron_val <= data;
            end else begin
                neuron_val <= neuron_mem[input_addr];
            end 

            if (write_enable) begin
                neuron_mem[output_addr] <= data;
            end
        end
    end

endmodule

mlp_v1/v3/control_unit.v
module control_unit 
    (   
        input clk, 
        input reset,
        output reg [11:0] input_neuron_addr,
        output reg [11:0] output_neuron_addr,
        // 16 bits
        output reg [15:0] input_weight_addr,
        output reg reset_mult_acc,
        output reg write_neuron,
        output reg done
    );

    //////// neuron count array ////////
    parameter layers = 4;    // number of layers including input/output
    reg [7:0] neuron_count_array [layers - 1 : 0];  

    //////// variables ////////
    reg [9:0]  weight_ptr;
    reg [3:0]  neuron_ptr;
    reg [1:0]  layer_ptr;
    

    always @(posedge clk) begin
        if (reset) begin 
            neuron_count_array[0] = 8'h04;
            neuron_count_array[1] = 8'h02;
            neuron_count_array[2] = 8'h02;
            neuron_count_array[3] = 8'h01;

            weight_ptr <= 0;
            neuron_ptr <= 0;
            layer_ptr <= 0;

            input_neuron_addr <= 0;
            output_neuron_addr <= 0;
            input_weight_addr <= 0;
            
            done <= 0;
            write_neuron <= 0;
            reset_mult_acc <= 1; 
        end else begin
            // Last weight for current neuron, move to the next neuron 
            if (weight_ptr == neuron_count_array[layer_ptr] - 1) begin
        
                // Last neuron in current layer, move to the next layer
                if ((neuron_ptr + 1) == neuron_count_array[(layer_ptr + 1)]) begin

                    // Finished MLP calculations, proceed to softmax
                    if (neuron_count_array[(layer_ptr + 1)] == 1) begin 
                        done <= 1;
                    end else begin 
                        done <= 0;
                        layer_ptr <= layer_ptr + 1;
                        neuron_ptr <= 0;
                    end
                end else begin 
                    neuron_ptr <= neuron_ptr + 1;
                end

                weight_ptr <= 0;
                write_neuron <= 1;
                reset_mult_acc <= 1; 
            end else begin
                weight_ptr <= weight_ptr + 1;
                write_neuron <= 0;
                reset_mult_acc <= 0;
            end

            // input neuron address = layer_ptr | weight_ptr, 12 bits 
            input_neuron_addr <= {layer_ptr, weight_ptr};

            // output neuron address = layer_ptr + 1| neuron_ptr, 12 bits
            output_neuron_addr <= {(layer_ptr + 2'b01), 6'b000000, neuron_ptr};

            // weight address = layer_ptr | neuron_ptr | weight_ptr, 16 bits
            input_weight_addr <= {layer_ptr, neuron_ptr, weight_ptr};
        end  
    end

endmodule

mlp_v1/v3_2/top.v
module top 
    (
        input clk, 
        input reset, 
        output wire signed [15:0] out,
        output wire finished
    );

    // Internal signals
    wire [11:0] neuron_addr;
    wire [15:0] weight_addr;
    wire [7:0] bias_addr;

    wire [11:0] out_neuron_addr_1;
    wire [11:0] out_neuron_addr_2;
    wire [11:0] out_neuron_addr_3;

    wire reset_mu_1;
    wire reset_mu_2;
    wire reset_mu_3;

    wire write_neuron_1;
    wire write_neuron_2;
    wire write_neuron_3;

    wire done_1;
    wire done_2;
    wire done_3;

    wire [15:0] neuron_val;
    wire [7:0] weight_val;
    wire [7:0] bias_val;

    wire [15:0] mu_out;
    wire [15:0] ru_out;

    control_unit cu (
        .clk(clk),
        .reset(reset),
        .input_neuron_addr(neuron_addr),
        .output_neuron_addr(out_neuron_addr_1),
        .input_weight_addr(weight_addr),
        .reset_mult_acc(reset_mu_1),
        .write_neuron(write_neuron_1),
        .done(done_1)
    );

    neuron_mem nm (
        .clk(clk),
        .reset(reset),
        .write_enable(write_neuron_3),
        .input_addr(neuron_addr),
        .data(ru_out),
        .output_addr(out_neuron_addr_3),
        .neuron_val(neuron_val)
    );

    weight_mem wm (
        .clk(clk),
        .reset(reset),
        .input_addr(weight_addr),
        .weight_val(weight_val)
    );

    bias_mem bm (
        .clk(clk),
        .reset(reset),
        .input_addr(weight_addr),
        .bias_val(bias_val)
    );

    multiply_unit mu (   
        .clk(clk),
        .reset(reset_mu_3 || reset),
        .op1(neuron_val),
        .op2(weight_val),
        .bias(bias_val),
        .out(mu_out)
    );

    relu ru(
        .in(mu_out),
        .out(ru_out)
    );

    softmax su(
        .clk(clk), 
        .reset(reset),
        .done(done_3),
        .in(ru_out), 
        .finished(finished),
        .result(out)
    );

    buffer b1(
        .clk(clk), 
        .reset(reset),

        .reset_mu_in(reset_mu_1),
        .done_in(done_1),
        .write_neuron_in(write_neuron_1),
        .out_neuron_addr_in(out_neuron_addr_1),

        .reset_mu_out(reset_mu_2),
        .done_out(done_2),
        .write_neuron_out(write_neuron_2),
        .out_neuron_addr_out(out_neuron_addr_2)
    );

    buffer b2(
        .clk(clk), 
        .reset(reset),

        .reset_mu_in(reset_mu_2),
        .done_in(done_2),
        .write_neuron_in(write_neuron_2),
        .out_neuron_addr_in(out_neuron_addr_2),

        .reset_mu_out(reset_mu_3),
        .done_out(done_3),
        .write_neuron_out(write_neuron_3),
        .out_neuron_addr_out(out_neuron_addr_3)
    );

endmodule

mlp_v1/v3/top_tb.v
`timescale 1ns / 1ps

module top_tb;

    // Declare testbench signals
    reg clk;
    reg reset;
    wire [15:0] out;
    wire finished;

    // Instantiate the DUT (Device Under Test)
    top uut (
        .clk(clk),
        .reset(reset),
        .out(out),
        .finished(finished)
    );

    always #10 clk = ~clk; 

    initial begin
        clk = 1;
        reset = 1;

        #20
        reset = 0;
        
        // Wait and observe outputs
        #400; 

        reset = 1;

        #20;

        reset = 0;

        #400;

        $finish;
    end

    initial begin
        $dumpfile("wave.vcd");  
        $dumpvars(0, uut);
    end

endmodule

mlp_v1/v3/wave.vcd
$date
	Fri Apr 11 13:49:04 2025
$end
$version
	Icarus Verilog
$end
$timescale
	1ps
$end
$scope module top_tb $end
$scope module uut $end
$var wire 1 ! clk $end
$var wire 1 " reset $end
$var wire 1 # write_neuron_3 $end
$var wire 1 $ write_neuron_2 $end
$var wire 1 % write_neuron_1 $end
$var wire 8 & weight_val [7:0] $end
$var wire 16 ' weight_addr [15:0] $end
$var wire 16 ( ru_out [15:0] $end
$var wire 1 ) reset_mu_3 $end
$var wire 1 * reset_mu_2 $end
$var wire 1 + reset_mu_1 $end
$var wire 12 , out_neuron_addr_3 [11:0] $end
$var wire 12 - out_neuron_addr_2 [11:0] $end
$var wire 12 . out_neuron_addr_1 [11:0] $end
$var wire 16 / out [15:0] $end
$var wire 16 0 neuron_val [15:0] $end
$var wire 12 1 neuron_addr [11:0] $end
$var wire 16 2 mu_out [15:0] $end
$var wire 1 3 finished $end
$var wire 1 4 done_3 $end
$var wire 1 5 done_2 $end
$var wire 1 6 done_1 $end
$var wire 8 7 bias_val [7:0] $end
$scope module b1 $end
$var wire 1 ! clk $end
$var wire 1 " reset $end
$var wire 1 % write_neuron_in $end
$var wire 1 + reset_mu_in $end
$var wire 12 8 out_neuron_addr_in [11:0] $end
$var wire 1 6 done_in $end
$var reg 1 5 done_out $end
$var reg 12 9 out_neuron_addr_out [11:0] $end
$var reg 1 * reset_mu_out $end
$var reg 1 $ write_neuron_out $end
$upscope $end
$scope module b2 $end
$var wire 1 ! clk $end
$var wire 1 5 done_in $end
$var wire 12 : out_neuron_addr_in [11:0] $end
$var wire 1 " reset $end
$var wire 1 * reset_mu_in $end
$var wire 1 $ write_neuron_in $end
$var reg 1 4 done_out $end
$var reg 12 ; out_neuron_addr_out [11:0] $end
$var reg 1 ) reset_mu_out $end
$var reg 1 # write_neuron_out $end
$upscope $end
$scope module bm $end
$var wire 1 ! clk $end
$var wire 1 " reset $end
$var wire 16 < input_addr [15:0] $end
$var wire 6 = bias_addr [5:0] $end
$var reg 8 > bias_val [7:0] $end
$upscope $end
$scope module cu $end
$var wire 1 ! clk $end
$var wire 1 " reset $end
$var parameter 32 ? layers $end
$var reg 1 6 done $end
$var reg 12 @ input_neuron_addr [11:0] $end
$var reg 16 A input_weight_addr [15:0] $end
$var reg 2 B layer_ptr [1:0] $end
$var reg 4 C neuron_ptr [3:0] $end
$var reg 12 D output_neuron_addr [11:0] $end
$var reg 1 + reset_mult_acc $end
$var reg 10 E weight_ptr [9:0] $end
$var reg 1 % write_neuron $end
$upscope $end
$scope module mu $end
$var wire 8 F bias [7:0] $end
$var wire 1 ! clk $end
$var wire 1 G reset $end
$var wire 8 H op2 [7:0] $end
$var wire 16 I op1 [15:0] $end
$var reg 16 J out [15:0] $end
$var reg 16 K product [15:0] $end
$var reg 16 L sum [15:0] $end
$upscope $end
$scope module nm $end
$var wire 1 ! clk $end
$var wire 12 M input_addr [11:0] $end
$var wire 12 N output_addr [11:0] $end
$var wire 1 " reset $end
$var wire 1 # write_enable $end
$var wire 16 O data [15:0] $end
$var reg 16 P neuron_val [15:0] $end
$upscope $end
$scope module ru $end
$var wire 16 Q in [15:0] $end
$var reg 16 R out [15:0] $end
$upscope $end
$scope module su $end
$var wire 1 ! clk $end
$var wire 1 4 done $end
$var wire 16 S in [15:0] $end
$var wire 1 " reset $end
$var reg 1 3 finished $end
$var reg 1 T prev_done $end
$var reg 16 U result [15:0] $end
$upscope $end
$scope module wm $end
$var wire 1 ! clk $end
$var wire 16 V input_addr [15:0] $end
$var wire 1 " reset $end
$var reg 8 W weight_val [7:0] $end
$upscope $end
$upscope $end
$upscope $end
$enddefinitions $end
$comment Show the parameter values. $end
$dumpall
b100 ?
$end
#0
$dumpvars
b0 W
b0 V
b0 U
0T
bx S
bx R
bx Q
b0 P
bx O
b0 N
b0 M
bx L
bx K
bx J
b0 I
b0 H
1G
b0 F
b0 E
b0 D
b0 C
b0 B
b0 A
b0 @
b0 >
b0 =
b0 <
b0 ;
b0 :
b0 9
b0 8
b0 7
06
05
04
03
bx 2
b0 1
b0 0
b0 /
b0 .
b0 -
b0 ,
1+
0*
0)
bx (
b0 '
b0 &
0%
0$
0#
1"
1!
$end
#10000
0!
#20000
1*
b1010000 7
b1010000 >
b1010000 F
b11111101 &
b11111101 H
b11111101 W
b111 0
b111 I
b111 P
b10000000000 .
b10000000000 8
b10000000000 D
0+
b1 E
b0 K
0G
1!
0"
#30000
0!
#40000
1G
b1 '
b1 <
b1 A
b1 V
b1 1
b1 @
b1 M
b10 E
b10000000000 -
b10000000000 9
b10000000000 :
0*
1)
b1111111111101011 K
1!
#50000
0!
#60000
0G
b10000000000 ,
b10000000000 ;
b10000000000 N
0)
b1110 &
b1110 H
b1110 W
b11 0
b11 I
b11 P
b10 '
b10 <
b10 A
b10 V
b10 1
b10 @
b10 M
b11 E
b111011 (
b111011 O
b111011 R
b111011 S
b111011 2
b111011 J
b111011 Q
b1111111111101011 L
1!
#70000
0!
#80000
b11 '
b11 <
b11 A
b11 V
b11 1
b11 @
b11 M
1+
1%
b0 E
b1 C
b1111111111111000 0
b1111111111111000 I
b1111111111111000 P
b11 &
b11 H
b11 W
b1100101 (
b1100101 O
b1100101 R
b1100101 S
b1100101 2
b1100101 J
b1100101 Q
b10101 L
b101010 K
1!
#90000
0!
#100000
b1 =
1$
1*
b11111000 &
b11111000 H
b11111000 W
b101 0
b101 I
b101 P
b10000000000 '
b10000000000 <
b10000000000 A
b10000000000 V
b10000000001 .
b10000000001 8
b10000000001 D
b0 1
b0 @
b0 M
0+
0%
b1 E
b1001101 (
b1001101 O
b1001101 R
b1001101 S
b1001101 2
b1001101 J
b1001101 Q
b1111111111111101 L
b1111111111101000 K
1!
#110000
0!
#120000
1G
b10000000001 '
b10000000001 <
b10000000001 A
b10000000001 V
b1 1
b1 @
b1 M
b10 E
b111 0
b111 I
b111 P
b100 &
b100 H
b100 W
b10100000 7
b10100000 >
b10100000 F
b10000000001 -
b10000000001 9
b10000000001 :
0$
0*
1#
1)
b100101 (
b100101 O
b100101 R
b100101 S
b100101 2
b100101 J
b100101 Q
b1111111111010101 L
b1111111111011000 K
1!
#130000
0!
#140000
0G
b10000000001 ,
b10000000001 ;
b10000000001 N
0#
0)
b11111010 &
b11111010 H
b11111010 W
b11 0
b11 I
b11 P
b10000000010 '
b10000000010 <
b10000000010 A
b10000000010 V
b10 1
b10 @
b10 M
b11 E
b0 (
b0 O
b0 R
b0 S
b1111111110111100 2
b1111111110111100 J
b1111111110111100 Q
b11100 L
b11100 K
1!
#150000
0!
#160000
b10000000011 '
b10000000011 <
b10000000011 A
b10000000011 V
b11 1
b11 @
b11 M
1+
1%
b0 E
b0 C
b1 B
b1111111111111000 0
b1111111111111000 I
b1111111111111000 P
b10000 &
b10000 H
b10000 W
b1111111110101010 2
b1111111110101010 J
b1111111110101010 Q
b1010 L
b1111111111101110 K
1!
#170000
0!
#180000
b10000 =
1$
1*
b1000 &
b1000 H
b1000 W
b101 0
b101 I
b101 P
b100000000000000 '
b100000000000000 <
b100000000000000 A
b100000000000000 V
b100000000000 .
b100000000000 8
b100000000000 D
b10000000000 1
b10000000000 @
b10000000000 M
0+
0%
b1 E
b1111111100101010 2
b1111111100101010 J
b1111111100101010 Q
b1111111110001010 L
b1111111110000000 K
1!
#190000
0!
#200000
1G
b100000000000001 '
b100000000000001 <
b100000000000001 A
b100000000000001 V
b10000000001 1
b10000000001 @
b10000000001 M
1+
1%
b0 E
b1 C
b100101 0
b100101 I
b100101 P
b11111100 &
b11111100 H
b11111100 W
b11110010 7
b11110010 >
b11110010 F
b100000000000 -
b100000000000 9
b100000000000 :
0$
0*
1#
1)
b1111111101010010 2
b1111111101010010 J
b1111111101010010 Q
b1111111110110010 L
b101000 K
1!
#210000
0!
#220000
0G
b10001 =
b100000000000 ,
b100000000000 ;
b100000000000 N
0#
0)
1$
1*
b11111011 &
b11111011 H
b11111011 W
b0 0
b0 I
b0 P
b100010000000000 '
b100010000000000 <
b100010000000000 A
b100010000000000 V
b100000000001 .
b100000000001 8
b100000000001 D
b10000000000 1
b10000000000 @
b10000000000 M
0+
0%
b1 E
b1111111101011110 2
b1111111101011110 J
b1111111101011110 Q
b1111111101101100 L
b1111111101101100 K
1!
#230000
0!
#240000
1G
b100010000000001 '
b100010000000001 <
b100010000000001 A
b100010000000001 V
b10000000001 1
b10000000001 @
b10000000001 M
1+
1%
b0 E
b0 C
b10 B
b100101 0
b100101 I
b100101 P
b110 &
b110 H
b110 W
b1001001 7
b1001001 >
b1001001 F
b100000000001 -
b100000000001 9
b100000000001 :
0$
0*
1#
1)
b0 K
1!
#250000
0!
#260000
0G
b100000 =
b100000000001 ,
b100000000001 ;
b100000000001 N
0#
0)
1$
1*
b10 &
b10 H
b10 W
b0 0
b0 I
b0 P
b1000000000000000 '
b1000000000000000 <
b1000000000000000 A
b1000000000000000 V
b110000000000 .
b110000000000 8
b110000000000 D
b100000000000 1
b100000000000 @
b100000000000 M
0+
0%
b1 E
b100100111 (
b100100111 O
b100100111 R
b100100111 S
b100100111 2
b100100111 J
b100100111 Q
b11011110 L
b11011110 K
1!
#270000
0!
#280000
1G
b1000000000000001 '
b1000000000000001 <
b1000000000000001 A
b1000000000000001 V
b100000000001 1
b100000000001 @
b100000000001 M
1+
1%
b0 E
16
b11 &
b11 H
b11 W
b1110000 7
b1110000 >
b1110000 F
b110000000000 -
b110000000000 9
b110000000000 :
0$
0*
1#
1)
b0 K
1!
#290000
0!
#300000
0G
b110000000000 ,
b110000000000 ;
b110000000000 N
0#
0)
1$
15
1*
b10 &
b10 H
b10 W
b100100111 0
b100100111 I
b100100111 P
b1000000000000000 '
b1000000000000000 <
b1000000000000000 A
b1000000000000000 V
b100000000000 1
b100000000000 @
b100000000000 M
0+
0%
b1 E
b1110000 (
b1110000 O
b1110000 R
b1110000 S
b1110000 2
b1110000 J
b1110000 Q
b0 L
1!
#310000
0!
#320000
1G
b1000000000000001 '
b1000000000000001 <
b1000000000000001 A
b1000000000000001 V
b100000000001 1
b100000000001 @
b100000000001 M
1+
1%
b0 E
b0 0
b0 I
b0 P
b11 &
b11 H
b11 W
0$
0*
1#
14
1)
b1010111110 (
b1010111110 O
b1010111110 R
b1010111110 S
b1010111110 2
b1010111110 J
b1010111110 Q
b1001001110 L
b1001001110 K
1!
#330000
0!
#340000
0G
0#
0)
1$
1*
b1010111110 /
b1010111110 U
13
1T
b10 &
b10 H
b10 W
b100100111 0
b100100111 I
b100100111 P
b1000000000000000 '
b1000000000000000 <
b1000000000000000 A
b1000000000000000 V
b100000000000 1
b100000000000 @
b100000000000 M
0+
0%
b1 E
b1110000 (
b1110000 O
b1110000 R
b1110000 S
b1110000 2
b1110000 J
b1110000 Q
b0 L
b0 K
1!
#350000
0!
#360000
1G
b1000000000000001 '
b1000000000000001 <
b1000000000000001 A
b1000000000000001 V
b100000000001 1
b100000000001 @
b100000000001 M
1+
1%
b0 E
b0 0
b0 I
b0 P
b11 &
b11 H
b11 W
03
0$
0*
1#
1)
b1010111110 (
b1010111110 O
b1010111110 R
b1010111110 S
b1010111110 2
b1010111110 J
b1010111110 Q
b1001001110 L
b1001001110 K
1!
#370000
0!
#380000
0G
0#
0)
1$
1*
b10 &
b10 H
b10 W
b100100111 0
b100100111 I
b100100111 P
b1000000000000000 '
b1000000000000000 <
b1000000000000000 A
b1000000000000000 V
b100000000000 1
b100000000000 @
b100000000000 M
0+
0%
b1 E
b1110000 (
b1110000 O
b1110000 R
b1110000 S
b1110000 2
b1110000 J
b1110000 Q
b0 L
b0 K
1!
#390000
0!
#400000
1G
b1000000000000001 '
b1000000000000001 <
b1000000000000001 A
b1000000000000001 V
b100000000001 1
b100000000001 @
b100000000001 M
1+
1%
b0 E
b0 0
b0 I
b0 P
b11 &
b11 H
b11 W
0$
0*
1#
1)
b1010111110 (
b1010111110 O
b1010111110 R
b1010111110 S
b1010111110 2
b1010111110 J
b1010111110 Q
b1001001110 L
b1001001110 K
1!
#410000
0!
#420000
b0 =
b0 ,
b0 ;
b0 N
0#
04
0)
b0 -
b0 9
b0 :
05
0T
b0 /
b0 U
b0 7
b0 >
b0 F
b0 &
b0 H
b0 W
0%
06
b0 '
b0 <
b0 A
b0 V
b0 .
b0 8
b0 D
b0 1
b0 @
b0 M
b0 B
b1110000 (
b1110000 O
b1110000 R
b1110000 S
b1110000 2
b1110000 J
b1110000 Q
b0 L
b0 K
1!
1"
#430000
0!
#440000
b10000000000 .
b10000000000 8
b10000000000 D
0+
b1 E
b111 0
b111 I
b111 P
b11111101 &
b11111101 H
b11111101 W
b1010000 7
b1010000 >
b1010000 F
1*
b0 (
b0 O
b0 R
b0 S
b0 2
b0 J
b0 Q
0G
1!
0"
#450000
0!
#460000
1G
1)
b10000000000 -
b10000000000 9
b10000000000 :
0*
b1 '
b1 <
b1 A
b1 V
b1 1
b1 @
b1 M
b10 E
b111011 (
b111011 O
b111011 R
b111011 S
b111011 2
b111011 J
b111011 Q
b1111111111101011 L
b1111111111101011 K
1!
#470000
0!
#480000
0G
b10 '
b10 <
b10 A
b10 V
b10 1
b10 @
b10 M
b11 E
b11 0
b11 I
b11 P
b1110 &
b1110 H
b1110 W
b10000000000 ,
b10000000000 ;
b10000000000 N
0)
1!
#490000
0!
#500000
b11 &
b11 H
b11 W
b1111111111111000 0
b1111111111111000 I
b1111111111111000 P
b11 '
b11 <
b11 A
b11 V
b11 1
b11 @
b11 M
1+
1%
b0 E
b1 C
b1100101 (
b1100101 O
b1100101 R
b1100101 S
b1100101 2
b1100101 J
b1100101 Q
b10101 L
b101010 K
1!
#510000
0!
#520000
b1 =
b10000000000 '
b10000000000 <
b10000000000 A
b10000000000 V
b10000000001 .
b10000000001 8
b10000000001 D
b0 1
b0 @
b0 M
0+
0%
b1 E
b101 0
b101 I
b101 P
b11111000 &
b11111000 H
b11111000 W
1$
1*
b1001101 (
b1001101 O
b1001101 R
b1001101 S
b1001101 2
b1001101 J
b1001101 Q
b1111111111111101 L
b1111111111101000 K
1!
#530000
0!
#540000
1G
1#
1)
b10000000001 -
b10000000001 9
b10000000001 :
0$
0*
b10100000 7
b10100000 >
b10100000 F
b100 &
b100 H
b100 W
b111 0
b111 I
b111 P
b10000000001 '
b10000000001 <
b10000000001 A
b10000000001 V
b1 1
b1 @
b1 M
b10 E
b100101 (
b100101 O
b100101 R
b100101 S
b100101 2
b100101 J
b100101 Q
b1111111111010101 L
b1111111111011000 K
1!
#550000
0!
#560000
0G
b10000000010 '
b10000000010 <
b10000000010 A
b10000000010 V
b10 1
b10 @
b10 M
b11 E
b11 0
b11 I
b11 P
b11111010 &
b11111010 H
b11111010 W
b10000000001 ,
b10000000001 ;
b10000000001 N
0#
0)
b0 (
b0 O
b0 R
b0 S
b1111111110111100 2
b1111111110111100 J
b1111111110111100 Q
b11100 L
b11100 K
1!
#570000
0!
#580000
b10000 &
b10000 H
b10000 W
b1111111111111000 0
b1111111111111000 I
b1111111111111000 P
b10000000011 '
b10000000011 <
b10000000011 A
b10000000011 V
b11 1
b11 @
b11 M
1+
1%
b0 E
b0 C
b1 B
b1111111110101010 2
b1111111110101010 J
b1111111110101010 Q
b1010 L
b1111111111101110 K
1!
#590000
0!
#600000
b10000 =
b100000000000000 '
b100000000000000 <
b100000000000000 A
b100000000000000 V
b100000000000 .
b100000000000 8
b100000000000 D
b10000000000 1
b10000000000 @
b10000000000 M
0+
0%
b1 E
b101 0
b101 I
b101 P
b1000 &
b1000 H
b1000 W
1$
1*
b1111111100101010 2
b1111111100101010 J
b1111111100101010 Q
b1111111110001010 L
b1111111110000000 K
1!
#610000
0!
#620000
1G
1#
1)
b100000000000 -
b100000000000 9
b100000000000 :
0$
0*
b11110010 7
b11110010 >
b11110010 F
b11111100 &
b11111100 H
b11111100 W
b100101 0
b100101 I
b100101 P
b100000000000001 '
b100000000000001 <
b100000000000001 A
b100000000000001 V
b10000000001 1
b10000000001 @
b10000000001 M
1+
1%
b0 E
b1 C
b1111111101010010 2
b1111111101010010 J
b1111111101010010 Q
b1111111110110010 L
b101000 K
1!
#630000
0!
#640000
b10001 =
0G
b100010000000000 '
b100010000000000 <
b100010000000000 A
b100010000000000 V
b100000000001 .
b100000000001 8
b100000000001 D
b10000000000 1
b10000000000 @
b10000000000 M
0+
0%
b1 E
b0 0
b0 I
b0 P
b11111011 &
b11111011 H
b11111011 W
1$
1*
b100000000000 ,
b100000000000 ;
b100000000000 N
0#
0)
b1111111101011110 2
b1111111101011110 J
b1111111101011110 Q
b1111111101101100 L
b1111111101101100 K
1!
#650000
0!
#660000
1G
1#
1)
b100000000001 -
b100000000001 9
b100000000001 :
0$
0*
b1001001 7
b1001001 >
b1001001 F
b110 &
b110 H
b110 W
b100101 0
b100101 I
b100101 P
b100010000000001 '
b100010000000001 <
b100010000000001 A
b100010000000001 V
b10000000001 1
b10000000001 @
b10000000001 M
1+
1%
b0 E
b0 C
b10 B
b0 K
1!
#670000
0!
#680000
b100000 =
0G
b1000000000000000 '
b1000000000000000 <
b1000000000000000 A
b1000000000000000 V
b110000000000 .
b110000000000 8
b110000000000 D
b100000000000 1
b100000000000 @
b100000000000 M
0+
0%
b1 E
b0 0
b0 I
b0 P
b10 &
b10 H
b10 W
1$
1*
b100000000001 ,
b100000000001 ;
b100000000001 N
0#
0)
b100100111 (
b100100111 O
b100100111 R
b100100111 S
b100100111 2
b100100111 J
b100100111 Q
b11011110 L
b11011110 K
1!
#690000
0!
#700000
1G
1#
1)
b110000000000 -
b110000000000 9
b110000000000 :
0$
0*
b1110000 7
b1110000 >
b1110000 F
b11 &
b11 H
b11 W
b1000000000000001 '
b1000000000000001 <
b1000000000000001 A
b1000000000000001 V
b100000000001 1
b100000000001 @
b100000000001 M
1+
1%
b0 E
16
b0 K
1!
#710000
0!
#720000
0G
b1000000000000000 '
b1000000000000000 <
b1000000000000000 A
b1000000000000000 V
b100000000000 1
b100000000000 @
b100000000000 M
0+
0%
b1 E
b100100111 0
b100100111 I
b100100111 P
b10 &
b10 H
b10 W
1$
15
1*
b110000000000 ,
b110000000000 ;
b110000000000 N
0#
0)
b1110000 (
b1110000 O
b1110000 R
b1110000 S
b1110000 2
b1110000 J
b1110000 Q
b0 L
1!
#730000
0!
#740000
1G
1#
14
1)
0$
0*
b11 &
b11 H
b11 W
b0 0
b0 I
b0 P
b1000000000000001 '
b1000000000000001 <
b1000000000000001 A
b1000000000000001 V
b100000000001 1
b100000000001 @
b100000000001 M
1+
1%
b0 E
b1010111110 (
b1010111110 O
b1010111110 R
b1010111110 S
b1010111110 2
b1010111110 J
b1010111110 Q
b1001001110 L
b1001001110 K
1!
#750000
0!
#760000
0G
b1000000000000000 '
b1000000000000000 <
b1000000000000000 A
b1000000000000000 V
b100000000000 1
b100000000000 @
b100000000000 M
0+
0%
b1 E
b100100111 0
b100100111 I
b100100111 P
b10 &
b10 H
b10 W
b1010111110 /
b1010111110 U
13
1T
1$
1*
0#
0)
b1110000 (
b1110000 O
b1110000 R
b1110000 S
b1110000 2
b1110000 J
b1110000 Q
b0 L
b0 K
1!
#770000
0!
#780000
1G
1#
1)
0$
0*
03
b11 &
b11 H
b11 W
b0 0
b0 I
b0 P
b1000000000000001 '
b1000000000000001 <
b1000000000000001 A
b1000000000000001 V
b100000000001 1
b100000000001 @
b100000000001 M
1+
1%
b0 E
b1010111110 (
b1010111110 O
b1010111110 R
b1010111110 S
b1010111110 2
b1010111110 J
b1010111110 Q
b1001001110 L
b1001001110 K
1!
#790000
0!
#800000
0G
b1000000000000000 '
b1000000000000000 <
b1000000000000000 A
b1000000000000000 V
b100000000000 1
b100000000000 @
b100000000000 M
0+
0%
b1 E
b100100111 0
b100100111 I
b100100111 P
b10 &
b10 H
b10 W
1$
1*
0#
0)
b1110000 (
b1110000 O
b1110000 R
b1110000 S
b1110000 2
b1110000 J
b1110000 Q
b0 L
b0 K
1!
#810000
0!
