mlp_v1/positive_test_v1/buffer_3.v
module buffer_3 (   
        input clk, 
        input reset,
        
        input done_3,
        input [15:0] out_3,
        input [11:0] out_neuron_addr_3,
        input write_neuron_3,

        output reg done_4,
        output reg [15:0] out_4,
        output reg [11:0] out_neuron_addr_4,
        output reg write_neuron_4
    );

    initial begin
        done_4 <= 0;
        out_4 <= 16'b0;
        out_neuron_addr_4 <= 12'b0;
        write_neuron_4 <= 0;
    end

    always @(posedge clk) begin
        if (reset) begin
            done_4 <= 0;
            out_4 <= 16'b0;
            out_neuron_addr_4 <= 12'b0;
            write_neuron_4 <= 0;
        end else begin
            done_4 <= done_3;
            out_4 <= out_3;
            out_neuron_addr_4 <= out_neuron_addr_3;
            write_neuron_4 <= write_neuron_3;
        end
    end

endmodule

mlp_v1/positive_test_v1/buffer_2.v
module buffer_2 (   
        input clk, 
        input reset,
        
        input done_2,
        input [15:0] neuron_val_2,
        input [7:0] weight_val_2,
        input [7:0] bias_val_2,
        input reset_mult_acc_2,
        input [11:0] out_neuron_addr_2,
        input write_neuron_2,

        output reg done_3,
        output reg [15:0] neuron_val_3,
        output reg [7:0] weight_val_3,
        output reg [7:0] bias_val_3,
        output reg reset_mult_acc_3,
        output reg [11:0] out_neuron_addr_3,
        output reg write_neuron_3
    );

    initial begin
        done_3 <= 0;
        neuron_val_3 <= 16'b0;
        weight_val_3 <= 8'b0;
        bias_val_3 <= 8'b0;
        reset_mult_acc_3 <= 0;
        out_neuron_addr_3 <= 12'b0;
        write_neuron_3 <= 0;
    end

    always @(posedge clk) begin
        if (reset) begin
            done_3 <= 0;
            neuron_val_3 <= 16'b0;
            weight_val_3 <= 8'b0;
            bias_val_3 <= 8'b0;
            reset_mult_acc_3 <= 0;
            out_neuron_addr_3 <= 12'b0;
            write_neuron_3 <= 0;
        end else begin
            done_3 <= done_2;
            neuron_val_3 <= neuron_val_2;
            weight_val_3 <= weight_val_2;
            bias_val_3 <= bias_val_2;
            reset_mult_acc_3 <= reset_mult_acc_2;
            out_neuron_addr_3 <= out_neuron_addr_2;
            write_neuron_3 <= write_neuron_2;
        end
    end

endmodule

mlp_v1/positive_test_v1/buffer_1.v
module buffer_1 (   
        input clk, 
        input reset,

        input done_1,
        input [11:0] neuron_addr_1,
        input [15:0] weight_addr_1,
        input reset_mult_acc_1,
        input [11:0] out_neuron_addr_1,
        input write_neuron_1,

        output reg done_2,
        output reg [11:0] neuron_addr_2,
        output reg [15:0] weight_addr_2,
        output reg reset_mult_acc_2,
        output reg [11:0] out_neuron_addr_2,
        output reg write_neuron_2
    );

    initial begin
        done_2 <= 0;
        neuron_addr_2 <= 0;
        weight_addr_2 <= 0;
        reset_mult_acc_2 <= 0;
        out_neuron_addr_2 <= 0;
        write_neuron_2 <= 0;
    end

    always @(posedge clk) begin
        if (reset) begin
            done_2 <= 0;
            neuron_addr_2 <= 0;
            weight_addr_2 <= 0;
            reset_mult_acc_2 <= 0;
            out_neuron_addr_2 <= 0;
            write_neuron_2 <= 0;
        end else begin 
            done_2 <= done_1;
            neuron_addr_2 <= neuron_addr_1;
            weight_addr_2 <= weight_addr_1;
            reset_mult_acc_2 <= reset_mult_acc_1;
            out_neuron_addr_2 <= out_neuron_addr_1;
            write_neuron_2 <= write_neuron_1;
        end
    end
    
endmodule

mlp_v1/positive_test_v1/softmax.v
module softmax(
        input clk, 
        input done,
        input [15:0] in, 
        output reg finished, 
        output reg [15:0] result
    );

    reg prev_done;

    initial begin
        result <= 0;
        finished <= 0;
        prev_done <= 0;
    end

    always @(negedge clk) begin    
        prev_done <= done;

        if (done && ~prev_done) begin
            finished <= 1;
            result <= in;
        end else begin
            finished <= 0;
        end
    end

endmodule

mlp_v1/positive_test_v1/relu.v
module relu 
    (   
        input wire signed [15:0] in,
        input wire signed [7:0] bias,
        output reg signed [15:0] out
    );

    always @* begin
        if ((in + bias) < 0)
            out = 0;
        else
            out = in;
    end

endmodule

mlp_v1/positive_test_v1/multiply_unit.v
module multiply_unit 
    (   
        input wire clk,
        input wire reset,
        input wire signed [15:0] op1,
        input wire signed [7:0] op2,
        output reg signed [15:0] out
    );

    reg [15:0] product;
    reg [15:0] sum;

    initial begin
        sum <= 0;
        product <= 0;
        out <= 0;
    end 

    always @(negedge clk) begin
        product = op1 * op2;

        if (reset) begin
            sum = 0 + product;
        end else begin
            sum = sum + product;
        end

        out = sum;
    end
    
endmodule


// what to do in case of overflows???

mlp_v1/positive_test_v1/bias_mem.v
module bias_mem
    (
        input wire clk,
        input wire[15:0] input_addr,
        output reg signed [7:0] bias_val
    );

    wire [5:0] bias_addr = input_addr[15:10];

    // 3 * 16 + 1 (maximum number of possible output neurons)
    reg signed [7:0] bias_mem[0:48];

    initial begin 
        bias_mem[6'b000000] = 0;
        bias_mem[6'b000001] = 0;

        bias_mem[6'b010000] = 0;
        bias_mem[6'b010001] = 0;

        bias_mem[6'b100000] = 0;
    end

    always @(negedge clk) begin
        bias_val = bias_mem[bias_addr];
    end

endmodule

mlp_v1/weight_mem.v
module weight_mem
    (
        input wire clk, 
        input wire [15:0] input_addr,
        output reg signed [7:0] weight_val
    );

    // 2^16 (size of neuron address) requires 65536 addresses
    reg [7:0] weight_mem[0:65535];

    // initializing input layer
    initial begin
        // layer 0 neuron 0 
        weight_mem[16'h0000] <= 16'h06;
        weight_mem[16'h0001] <= 16'h03;
        weight_mem[16'h0002] <= 16'h0d;
        weight_mem[16'h0003] <= 16'h07;

        // layer 0 neuron 1
        weight_mem[16'h0400] <= 16'h09;
        weight_mem[16'h0401] <= 16'h04;
        weight_mem[16'h0402] <= 16'h04;
        weight_mem[16'h0403] <= 16'h03;

        // layer 1 neuron 0
        weight_mem[16'h4000] <= 16'h0e;
        weight_mem[16'h4001] <= 16'h03;

        // layer 1 neuron 1
        weight_mem[16'h4400] <= 16'h08;
        weight_mem[16'h4401] <= 16'h04;

        // layer 2 neuron 0
        weight_mem[16'h8000] <= 16'h02;
        weight_mem[16'h8001] <= 16'h03;

        weight_val <= 16'h00;        
    end

    always @(negedge clk) begin
        weight_val = weight_mem[input_addr];
    end

endmodule

mlp_v1/neuron_mem.v
module neuron_mem
    (
        input wire clk, 
        input wire write_enable,
        input wire [11:0] input_addr,
        input wire signed [15:0] data,
        input wire [11:0] output_addr,
        output reg signed [15:0] neuron_val
    );

    // 2^12 (size of neuron address) requires 4096 addresses
    reg [15:0] neuron_mem[0:4095];

    // initializing input layer
    initial begin
        neuron_val <=  16'h00;

        neuron_mem[0] <= 16'h07;
        neuron_mem[1] <= 16'h05;
        neuron_mem[2] <= 16'h09;
        neuron_mem[3] <= 16'h04;
    end

    always @(negedge clk) begin
        if (write_enable) begin
            neuron_mem[output_addr] = data;
        end

        neuron_val = neuron_mem[input_addr];
    end

endmodule

mlp_v1/positive_test_v1/control_unit.v
module control_unit 
    (   
        input clk, 
        input reset,
        output reg [11:0] input_neuron_addr,
        output reg [11:0] output_neuron_addr,
        // 16 bits
        output reg [15:0] input_weight_addr,
        output reg reset_mult_acc,
        output reg write_neuron,
        output reg done
    );



    //////// initialize outputs ////////
    initial begin
        reset_mult_acc = 0;            
        write_neuron = 0;              
        done = 0;  
        input_neuron_addr = 0;
        output_neuron_addr = 0;
        input_weight_addr = 0;
    end
    ////////////////////////////////////


    //////// neuron count array ////////
    parameter layers = 4;    // number of layers including input/output
    reg [7:0] neuron_count_array [layers - 1 : 0];  

    // providing values to neuron count array
    initial begin
        neuron_count_array[0] = 8'h04;
        neuron_count_array[1] = 8'h02;
        neuron_count_array[2] = 8'h02;
        neuron_count_array[3] = 8'h01;
    end
    ///////////////////////////////////



    //////// variables ////////
    reg [9:0]  weight_ptr;
    reg [3:0]  neuron_ptr;
    reg [1:0]  layer_ptr;

    initial begin
        weight_ptr = 10'b0;
        neuron_ptr = 4'b0;
        layer_ptr = 2'b0;
    end
    ///////////////////////////


    always @(negedge clk) begin
        if (!reset) begin 
            /////////////////////////////////////////////////////////////

            // Last weight for current neuron, move to the next neuron 
            if (weight_ptr == neuron_count_array[layer_ptr] - 1) begin
        
                // Last neuron in current layer, move to the next layer
                if ((neuron_ptr + 1) == neuron_count_array[(layer_ptr + 1)]) begin

                    // Finished MLP calculations, proceed to softmax
                    if (neuron_count_array[(layer_ptr + 1)] == 1) begin 
                        done = 1;
                    end else begin 
                        done = 0;
                        layer_ptr = layer_ptr + 1;
                        neuron_ptr = 0;
                    end
                end else begin 
                    neuron_ptr = neuron_ptr + 1;
                end

                weight_ptr = 0;
                write_neuron = 1;
                reset_mult_acc = 1; 
            end else begin
                weight_ptr = weight_ptr + 1;
                write_neuron = 0;
                reset_mult_acc = 0;
            end


            //////// Set addresses /////////////////////////////////////
            // (can be optimized with address bases)

            // input neuron address = layer_ptr | weight_ptr, 12 bits 
            input_neuron_addr = {layer_ptr, weight_ptr};

            // output neuron address = layer_ptr + 1| neuron_ptr, 12 bits
            output_neuron_addr = {(layer_ptr + 2'b01), 6'b000000, neuron_ptr};

            // weight address = layer_ptr | neuron_ptr | weight_ptr, 16 bits
            input_weight_addr = {layer_ptr, neuron_ptr, weight_ptr};   

        // if reset is true, i.e. we are restarting
        end else begin
            weight_ptr <= 0;
            neuron_ptr <= 0;
            layer_ptr <= 0;

            input_neuron_addr <= 0;
            output_neuron_addr <= 0;
            input_weight_addr <= 0;
            
            done <= 0;
            write_neuron <= 0;
            reset_mult_acc <= 0; 
        end  
    end

endmodule

mlp_v1/positive_test_v1/top.v
module top 
    (
        input clk, 
        input reset, 
        output wire signed [15:0] out,
        output wire finished
    );

    // Internal signals
    wire [11:0] neuron_addr_1;
    wire [11:0] neuron_addr_2;
    wire [15:0] weight_addr_1;
    wire [15:0] weight_addr_2;
    wire [7:0] bias_addr_1;
    wire [7:0] bias_addr_2;

    wire [11:0] out_neuron_addr_1;
    wire [11:0] out_neuron_addr_2;
    wire [11:0] out_neuron_addr_3;
    wire [11:0] out_neuron_addr_4;

    wire reset_mult_acc_1;
    wire reset_mult_acc_2;
    wire reset_mult_acc_3;

    wire write_neuron_1;
    wire write_neuron_2;
    wire write_neuron_3;
    wire write_neuron_4;

    wire done_1;
    wire done_2;
    wire done_3;
    wire done_4;
    
    wire [15:0] neuron_val_2;
    wire [15:0] neuron_val_3;
    wire [7:0] weight_val_2;
    wire [7:0] weight_val_3;
    wire [7:0] bias_val_2;
    wire [7:0] bias_val_3;

    wire [15:0] mult_out_3;
    wire [15:0] out_3;
    wire [15:0] out_4;

    control_unit cu (
        .clk(clk),
        .reset(reset),
        .input_neuron_addr(neuron_addr_1),
        .output_neuron_addr(out_neuron_addr_1),
        .input_weight_addr(weight_addr_1),
        .reset_mult_acc(reset_mult_acc_1),
        .write_neuron(write_neuron_1),
        .done(done_1)
    );

    neuron_mem nm (
        .clk(clk),
        .write_enable(reset_mult_acc_3),
        .input_addr(neuron_addr_2),
        .data(out_4),
        .output_addr(out_neuron_addr_4),
        .neuron_val(neuron_val_2)
    );

    weight_mem wm (
        .clk(clk),
        .input_addr(weight_addr_2),
        .weight_val(weight_val_2)
    );

    bias_mem bm (
        .clk(clk),
        .input_addr(weight_addr_2),
        .bias_val(bias_val_2)
    );

    multiply_unit mu (   
        .clk(clk),
        .reset(reset_mult_acc_3 || reset),
        .op1(neuron_val_3),
        .op2(weight_val_3),
        .out(mult_out_3)
    );

    relu ru(
        .in(mult_out_3),
        .bias(bias_val_3),
        .out(out_3)
    );

    softmax su(
        .clk(clk), 
        .done(done_3),
        .in(out_4), 
        .finished(finished),
        .result(out)
    );

    buffer_1 b1 (
        .clk(clk), 
        .reset(reset),
        
        .done_1(done_1),
        .neuron_addr_1(neuron_addr_1),
        .weight_addr_1(weight_addr_1),
        .reset_mult_acc_1(reset_mult_acc_1),
        .out_neuron_addr_1(out_neuron_addr_1),
        .write_neuron_1(write_neuron_1),

        .done_2(done_2),
        .neuron_addr_2(neuron_addr_2),
        .weight_addr_2(weight_addr_2),
        .reset_mult_acc_2(reset_mult_acc_2),
        .out_neuron_addr_2(out_neuron_addr_2),
        .write_neuron_2(write_neuron_2)
    );

    buffer_2 b2 (
        .clk(clk), 
        .reset(reset),
        
        .done_2(done_2),
        .neuron_val_2(neuron_val_2),
        .weight_val_2(weight_val_2),
        .bias_val_2(bias_val_2),
        .reset_mult_acc_2(reset_mult_acc_2),
        .out_neuron_addr_2(out_neuron_addr_2),
        .write_neuron_2(write_neuron_2),

        .done_3(done_3),
        .neuron_val_3(neuron_val_3),
        .weight_val_3(weight_val_3),
        .bias_val_3(bias_val_3),
        .reset_mult_acc_3(reset_mult_acc_3),
        .out_neuron_addr_3(out_neuron_addr_3),
        .write_neuron_3(write_neuron_3)
    );

    buffer_3 b3 (
        .clk(clk), 
        .reset(reset),
        
        .done_3(done_3),
        .out_3(out_3),
        .out_neuron_addr_3(out_neuron_addr_3),
        .write_neuron_3(write_neuron_3),

        .done_4(done_4),
        .out_4(out_4),
        .out_neuron_addr_4(out_neuron_addr_4),
        .write_neuron_4(write_neuron_4)
    );

endmodule

mlp_v1/positive_test_v1/top_tb.v
`timescale 1ns / 1ps

module top_tb;

    // Declare testbench signals
    reg clk;
    reg reset;
    wire [15:0] out;
    wire finished;

    // Instantiate the DUT (Device Under Test)
    top uut (
        .clk(clk),
        .reset(reset),
        .out(out),
        .finished(finished)
    );

    always #10 clk = ~clk; 

    initial begin
        clk = 0;
        reset = 1;

        #10
        reset = 0;
        
        // Wait and observe outputs
        #400; 

        reset = 1;

        #30;

        reset = 0;

        #400;

        $finish;
    end

    initial begin
        $dumpfile("wave.vcd");  
        $dumpvars(0, uut);
    end

endmodule

mlp_v1/positive_test_v1/wave.vcd
$date
	Thu Apr 10 17:25:56 2025
$end
$version
	Icarus Verilog
$end
$timescale
	1ps
$end
$scope module top_tb $end
$scope module uut $end
$var wire 1 ! clk $end
$var wire 1 " reset $end
$var wire 1 # write_neuron_4 $end
$var wire 1 $ write_neuron_3 $end
$var wire 1 % write_neuron_2 $end
$var wire 1 & write_neuron_1 $end
$var wire 8 ' weight_val_3 [7:0] $end
$var wire 8 ( weight_val_2 [7:0] $end
$var wire 16 ) weight_addr_2 [15:0] $end
$var wire 16 * weight_addr_1 [15:0] $end
$var wire 1 + reset_mult_acc_3 $end
$var wire 1 , reset_mult_acc_2 $end
$var wire 1 - reset_mult_acc_1 $end
$var wire 12 . out_neuron_addr_4 [11:0] $end
$var wire 12 / out_neuron_addr_3 [11:0] $end
$var wire 12 0 out_neuron_addr_2 [11:0] $end
$var wire 12 1 out_neuron_addr_1 [11:0] $end
$var wire 16 2 out_4 [15:0] $end
$var wire 16 3 out_3 [15:0] $end
$var wire 16 4 out [15:0] $end
$var wire 16 5 neuron_val_3 [15:0] $end
$var wire 16 6 neuron_val_2 [15:0] $end
$var wire 12 7 neuron_addr_2 [11:0] $end
$var wire 12 8 neuron_addr_1 [11:0] $end
$var wire 16 9 mult_out_3 [15:0] $end
$var wire 1 : finished $end
$var wire 1 ; done_4 $end
$var wire 1 < done_3 $end
$var wire 1 = done_2 $end
$var wire 1 > done_1 $end
$var wire 8 ? bias_val_3 [7:0] $end
$var wire 8 @ bias_val_2 [7:0] $end
$scope module b1 $end
$var wire 1 ! clk $end
$var wire 1 " reset $end
$var wire 1 & write_neuron_1 $end
$var wire 16 A weight_addr_1 [15:0] $end
$var wire 1 - reset_mult_acc_1 $end
$var wire 12 B out_neuron_addr_1 [11:0] $end
$var wire 12 C neuron_addr_1 [11:0] $end
$var wire 1 > done_1 $end
$var reg 1 = done_2 $end
$var reg 12 D neuron_addr_2 [11:0] $end
$var reg 12 E out_neuron_addr_2 [11:0] $end
$var reg 1 , reset_mult_acc_2 $end
$var reg 16 F weight_addr_2 [15:0] $end
$var reg 1 % write_neuron_2 $end
$upscope $end
$scope module b2 $end
$var wire 1 ! clk $end
$var wire 1 = done_2 $end
$var wire 12 G out_neuron_addr_2 [11:0] $end
$var wire 1 " reset $end
$var wire 1 , reset_mult_acc_2 $end
$var wire 1 % write_neuron_2 $end
$var wire 8 H weight_val_2 [7:0] $end
$var wire 16 I neuron_val_2 [15:0] $end
$var wire 8 J bias_val_2 [7:0] $end
$var reg 8 K bias_val_3 [7:0] $end
$var reg 1 < done_3 $end
$var reg 16 L neuron_val_3 [15:0] $end
$var reg 12 M out_neuron_addr_3 [11:0] $end
$var reg 1 + reset_mult_acc_3 $end
$var reg 8 N weight_val_3 [7:0] $end
$var reg 1 $ write_neuron_3 $end
$upscope $end
$scope module b3 $end
$var wire 1 ! clk $end
$var wire 1 < done_3 $end
$var wire 12 O out_neuron_addr_3 [11:0] $end
$var wire 1 " reset $end
$var wire 1 $ write_neuron_3 $end
$var wire 16 P out_3 [15:0] $end
$var reg 1 ; done_4 $end
$var reg 16 Q out_4 [15:0] $end
$var reg 12 R out_neuron_addr_4 [11:0] $end
$var reg 1 # write_neuron_4 $end
$upscope $end
$scope module bm $end
$var wire 1 ! clk $end
$var wire 16 S input_addr [15:0] $end
$var wire 6 T bias_addr [5:0] $end
$var reg 8 U bias_val [7:0] $end
$upscope $end
$scope module cu $end
$var wire 1 ! clk $end
$var wire 1 " reset $end
$var parameter 32 V layers $end
$var reg 1 > done $end
$var reg 12 W input_neuron_addr [11:0] $end
$var reg 16 X input_weight_addr [15:0] $end
$var reg 2 Y layer_ptr [1:0] $end
$var reg 4 Z neuron_ptr [3:0] $end
$var reg 12 [ output_neuron_addr [11:0] $end
$var reg 1 - reset_mult_acc $end
$var reg 10 \ weight_ptr [9:0] $end
$var reg 1 & write_neuron $end
$upscope $end
$scope module mu $end
$var wire 1 ! clk $end
$var wire 16 ] op1 [15:0] $end
$var wire 8 ^ op2 [7:0] $end
$var wire 1 _ reset $end
$var reg 16 ` out [15:0] $end
$var reg 16 a product [15:0] $end
$var reg 16 b sum [15:0] $end
$upscope $end
$scope module nm $end
$var wire 1 ! clk $end
$var wire 16 c data [15:0] $end
$var wire 12 d input_addr [11:0] $end
$var wire 12 e output_addr [11:0] $end
$var wire 1 + write_enable $end
$var reg 16 f neuron_val [15:0] $end
$upscope $end
$scope module ru $end
$var wire 8 g bias [7:0] $end
$var wire 16 h in [15:0] $end
$var reg 16 i out [15:0] $end
$upscope $end
$scope module su $end
$var wire 1 ! clk $end
$var wire 1 < done $end
$var wire 16 j in [15:0] $end
$var reg 1 : finished $end
$var reg 1 k prev_done $end
$var reg 16 l result [15:0] $end
$upscope $end
$scope module wm $end
$var wire 1 ! clk $end
$var wire 16 m input_addr [15:0] $end
$var reg 8 n weight_val [7:0] $end
$upscope $end
$upscope $end
$upscope $end
$enddefinitions $end
$comment Show the parameter values. $end
$dumpall
b100 V
$end
#0
$dumpvars
b0 n
b0 m
b0 l
xk
b0 j
b0 i
b0 h
b0 g
b0 f
b0 e
b0 d
b0 c
b0 b
b0 a
b0 `
1_
b0 ^
b0 ]
b0 \
b0 [
b0 Z
b0 Y
b0 X
b0 W
bx U
b0 T
b0 S
b0 R
b0 Q
b0 P
b0 O
b0 N
b0 M
b0 L
b0 K
bx J
b0 I
b0 H
b0 G
b0 F
b0 E
b0 D
b0 C
b0 B
b0 A
bx @
b0 ?
0>
0=
0<
0;
0:
b0 9
b0 8
b0 7
b0 6
b0 5
b0 4
b0 3
b0 2
b0 1
b0 0
b0 /
b0 .
0-
0,
0+
b0 *
b0 )
b0 (
b0 '
0&
0%
0$
0#
1"
0!
$end
#10000
bx ?
bx K
bx g
0_
0"
1!
#20000
0k
b0 @
b0 J
b0 U
b110 (
b110 H
b110 n
b111 6
b111 I
b111 f
b1 *
b1 A
b1 X
b10000000000 1
b10000000000 B
b10000000000 [
b1 8
b1 C
b1 W
b1 \
0!
#30000
b0 ?
b0 K
b0 g
b110 '
b110 N
b110 ^
b111 5
b111 L
b111 ]
b10000000000 0
b10000000000 E
b10000000000 G
b1 )
b1 F
b1 S
b1 m
b1 7
b1 D
b1 d
1!
#40000
b101010 3
b101010 P
b101010 i
b10 *
b10 A
b10 X
b10 8
b10 C
b10 W
b10 \
b101 6
b101 I
b101 f
b11 (
b11 H
b11 n
b101010 9
b101010 `
b101010 h
b101010 b
b101010 a
0!
#50000
b10 )
b10 F
b10 S
b10 m
b10 7
b10 D
b10 d
b10000000000 /
b10000000000 M
b10000000000 O
b11 '
b11 N
b11 ^
b101 5
b101 L
b101 ]
b101010 2
b101010 Q
b101010 c
b101010 j
1!
#60000
b111001 3
b111001 P
b111001 i
b111001 9
b111001 `
b111001 h
b111001 b
b1111 a
b1101 (
b1101 H
b1101 n
b1001 6
b1001 I
b1001 f
b11 *
b11 A
b11 X
b11 8
b11 C
b11 W
b11 \
0!
#70000
b10000000000 .
b10000000000 R
b10000000000 e
b111001 2
b111001 Q
b111001 c
b111001 j
b1101 '
b1101 N
b1101 ^
b1001 5
b1001 L
b1001 ]
b11 )
b11 F
b11 S
b11 m
b11 7
b11 D
b11 d
1!
#80000
b10101110 3
b10101110 P
b10101110 i
b10000000000 *
b10000000000 A
b10000000000 X
b10000000001 1
b10000000001 B
b10000000001 [
b0 8
b0 C
b0 W
1-
1&
b0 \
b1 Z
b100 6
b100 I
b100 f
b111 (
b111 H
b111 n
b10101110 9
b10101110 `
b10101110 h
b10101110 b
b1110101 a
0!
#90000
b1 T
1%
b10000000001 0
b10000000001 E
b10000000001 G
1,
b10000000000 )
b10000000000 F
b10000000000 S
b10000000000 m
b0 7
b0 D
b0 d
b111 '
b111 N
b111 ^
b100 5
b100 L
b100 ]
b10101110 2
b10101110 Q
b10101110 c
b10101110 j
1!
#100000
b11001010 3
b11001010 P
b11001010 i
b11001010 9
b11001010 `
b11001010 h
b11001010 b
b11100 a
b1001 (
b1001 H
b1001 n
b111 6
b111 I
b111 f
b10000000001 *
b10000000001 A
b10000000001 X
b1 8
b1 C
b1 W
0-
0&
b1 \
0!
#110000
1_
b11001010 2
b11001010 Q
b11001010 c
b11001010 j
1$
b10000000001 /
b10000000001 M
b10000000001 O
1+
b1001 '
b1001 N
b1001 ^
b111 5
b111 L
b111 ]
0%
0,
b10000000001 )
b10000000001 F
b10000000001 S
b10000000001 m
b1 7
b1 D
b1 d
1!
#120000
b111111 3
b111111 P
b111111 i
b10000000010 *
b10000000010 A
b10000000010 X
b10 8
b10 C
b10 W
b10 \
b101 6
b101 I
b101 f
b100 (
b100 H
b100 n
b111111 9
b111111 `
b111111 h
b111111 b
b111111 a
0!
#130000
0_
b10000000010 )
b10000000010 F
b10000000010 S
b10000000010 m
b10 7
b10 D
b10 d
0$
0+
b100 '
b100 N
b100 ^
b101 5
b101 L
b101 ]
1#
b10000000001 .
b10000000001 R
b10000000001 e
b111111 2
b111111 Q
b111111 c
b111111 j
1!
#140000
b1010011 3
b1010011 P
b1010011 i
b1010011 9
b1010011 `
b1010011 h
b1010011 b
b10100 a
b1001 6
b1001 I
b1001 f
b10000000011 *
b10000000011 A
b10000000011 X
b11 8
b11 C
b11 W
b11 \
0!
#150000
0#
b1010011 2
b1010011 Q
b1010011 c
b1010011 j
b1001 5
b1001 L
b1001 ]
b10000000011 )
b10000000011 F
b10000000011 S
b10000000011 m
b11 7
b11 D
b11 d
1!
#160000
b1110111 3
b1110111 P
b1110111 i
b100000000000000 *
b100000000000000 A
b100000000000000 X
b100000000000 1
b100000000000 B
b100000000000 [
b10000000000 8
b10000000000 C
b10000000000 W
1-
1&
b0 \
b0 Z
b1 Y
b100 6
b100 I
b100 f
b11 (
b11 H
b11 n
b1110111 9
b1110111 `
b1110111 h
b1110111 b
b100100 a
0!
#170000
b10000 T
1%
b100000000000 0
b100000000000 E
b100000000000 G
1,
b100000000000000 )
b100000000000000 F
b100000000000000 S
b100000000000000 m
b10000000000 7
b10000000000 D
b10000000000 d
b11 '
b11 N
b11 ^
b100 5
b100 L
b100 ]
b1110111 2
b1110111 Q
b1110111 c
b1110111 j
1!
#180000
b10000011 3
b10000011 P
b10000011 i
b10000011 9
b10000011 `
b10000011 h
b10000011 b
b1100 a
b1110 (
b1110 H
b1110 n
b11001010 6
b11001010 I
b11001010 f
b100000000000001 *
b100000000000001 A
b100000000000001 X
b10000000001 8
b10000000001 C
b10000000001 W
0-
0&
b1 \
0!
#190000
1_
b10000011 2
b10000011 Q
b10000011 c
b10000011 j
1$
b100000000000 /
b100000000000 M
b100000000000 O
1+
b1110 '
b1110 N
b1110 ^
b11001010 5
b11001010 L
b11001010 ]
0%
0,
b100000000000001 )
b100000000000001 F
b100000000000001 S
b100000000000001 m
b10000000001 7
b10000000001 D
b10000000001 d
1!
#200000
b101100001100 3
b101100001100 P
b101100001100 i
b100010000000000 *
b100010000000000 A
b100010000000000 X
b100000000001 1
b100000000001 B
b100000000001 [
b10000000000 8
b10000000000 C
b10000000000 W
1-
1&
b0 \
b1 Z
b10000011 6
b10000011 I
b10000011 f
b11 (
b11 H
b11 n
b101100001100 9
b101100001100 `
b101100001100 h
b101100001100 b
b101100001100 a
0!
#210000
b10001 T
0_
1%
b100000000001 0
b100000000001 E
b100000000001 G
1,
b100010000000000 )
b100010000000000 F
b100010000000000 S
b100010000000000 m
b10000000000 7
b10000000000 D
b10000000000 d
0$
0+
b11 '
b11 N
b11 ^
b10000011 5
b10000011 L
b10000011 ]
1#
b100000000000 .
b100000000000 R
b100000000000 e
b101100001100 2
b101100001100 Q
b101100001100 c
b101100001100 j
1!
#220000
b110010010101 3
b110010010101 P
b110010010101 i
b110010010101 9
b110010010101 `
b110010010101 h
b110010010101 b
b110001001 a
b1000 (
b1000 H
b1000 n
b11001010 6
b11001010 I
b11001010 f
b100010000000001 *
b100010000000001 A
b100010000000001 X
b10000000001 8
b10000000001 C
b10000000001 W
0-
0&
b1 \
0!
#230000
1_
0#
b110010010101 2
b110010010101 Q
b110010010101 c
b110010010101 j
1$
b100000000001 /
b100000000001 M
b100000000001 O
1+
b1000 '
b1000 N
b1000 ^
b11001010 5
b11001010 L
b11001010 ]
0%
0,
b100010000000001 )
b100010000000001 F
b100010000000001 S
b100010000000001 m
b10000000001 7
b10000000001 D
b10000000001 d
1!
#240000
b11001010000 3
b11001010000 P
b11001010000 i
b1000000000000000 *
b1000000000000000 A
b1000000000000000 X
b110000000000 1
b110000000000 B
b110000000000 [
b100000000000 8
b100000000000 C
b100000000000 W
1-
1&
b0 \
b0 Z
b10 Y
b10000011 6
b10000011 I
b10000011 f
b100 (
b100 H
b100 n
b11001010000 9
b11001010000 `
b11001010000 h
b11001010000 b
b11001010000 a
0!
#250000
b100000 T
0_
1%
b110000000000 0
b110000000000 E
b110000000000 G
1,
b1000000000000000 )
b1000000000000000 F
b1000000000000000 S
b1000000000000000 m
b100000000000 7
b100000000000 D
b100000000000 d
0$
0+
b100 '
b100 N
b100 ^
b10000011 5
b10000011 L
b10000011 ]
1#
b100000000001 .
b100000000001 R
b100000000001 e
b11001010000 2
b11001010000 Q
b11001010000 c
b11001010000 j
1!
#260000
b100001011100 3
b100001011100 P
b100001011100 i
b100001011100 9
b100001011100 `
b100001011100 h
b100001011100 b
b1000001100 a
b10 (
b10 H
b10 n
b110010010101 6
b110010010101 I
b110010010101 f
b1000000000000001 *
b1000000000000001 A
b1000000000000001 X
b100000000001 8
b100000000001 C
b100000000001 W
0-
0&
b1 \
0!
#270000
1_
0#
b100001011100 2
b100001011100 Q
b100001011100 c
b100001011100 j
1$
b110000000000 /
b110000000000 M
b110000000000 O
1+
b10 '
b10 N
b10 ^
b110010010101 5
b110010010101 L
b110010010101 ]
0%
0,
b1000000000000001 )
b1000000000000001 F
b1000000000000001 S
b1000000000000001 m
b100000000001 7
b100000000001 D
b100000000001 d
1!
#280000
b1100100101010 3
b1100100101010 P
b1100100101010 i
b1000000000000000 *
b1000000000000000 A
b1000000000000000 X
b100000000000 8
b100000000000 C
b100000000000 W
1-
1&
b0 \
1>
b100001011100 6
b100001011100 I
b100001011100 f
b11 (
b11 H
b11 n
b1100100101010 9
b1100100101010 `
b1100100101010 h
b1100100101010 b
b1100100101010 a
0!
#290000
0_
1%
1,
b1000000000000000 )
b1000000000000000 F
b1000000000000000 S
b1000000000000000 m
b100000000000 7
b100000000000 D
b100000000000 d
1=
0$
0+
b11 '
b11 N
b11 ^
b100001011100 5
b100001011100 L
b100001011100 ]
1#
b110000000000 .
b110000000000 R
b110000000000 e
b1100100101010 2
b1100100101010 Q
b1100100101010 c
b1100100101010 j
1!
#300000
b11001000111110 3
b11001000111110 P
b11001000111110 i
b11001000111110 9
b11001000111110 `
b11001000111110 h
b11001000111110 b
b1100100010100 a
b10 (
b10 H
b10 n
b110010010101 6
b110010010101 I
b110010010101 f
b1000000000000001 *
b1000000000000001 A
b1000000000000001 X
b100000000001 8
b100000000001 C
b100000000001 W
0-
0&
b1 \
0!
#310000
1_
0#
b11001000111110 2
b11001000111110 Q
b11001000111110 c
b11001000111110 j
1$
1+
b10 '
b10 N
b10 ^
b110010010101 5
b110010010101 L
b110010010101 ]
1<
0%
0,
b1000000000000001 )
b1000000000000001 F
b1000000000000001 S
b1000000000000001 m
b100000000001 7
b100000000001 D
b100000000001 d
1!
#320000
b11001000111110 4
b11001000111110 l
1:
1k
b1100100101010 3
b1100100101010 P
b1100100101010 i
b1000000000000000 *
b1000000000000000 A
b1000000000000000 X
b100000000000 8
b100000000000 C
b100000000000 W
1-
1&
b0 \
b100001011100 6
b100001011100 I
b100001011100 f
b11 (
b11 H
b11 n
b1100100101010 9
b1100100101010 `
b1100100101010 h
b1100100101010 b
b1100100101010 a
0!
