mlp_v1/v3_2/buffer.v
module buffer (   
        input clk, 
        input reset,

        input reset_mu_in,
        input done_in,
        input write_neuron_in,
        input [11:0] out_neuron_addr_in,

        output reg reset_mu_out,
        output reg done_out,
        output reg write_neuron_out,
        output reg [11:0] out_neuron_addr_out
    );

    always @(posedge clk) begin
        if (reset) begin
            reset_mu_out <= 0;
            done_out <= 0;
            write_neuron_out <= 0;
            out_neuron_addr_out <= 0;
        end else begin 
            reset_mu_out <= reset_mu_in;
            done_out <= done_in;
            write_neuron_out <= write_neuron_in;
            out_neuron_addr_out <= out_neuron_addr_in;
        end
    end
    
endmodule

mlp_v1/v3/softmax.v
module softmax(
        input clk, 
        input reset,
        input done,
        input [15:0] in, 
        output reg finished, 
        output reg [15:0] result
    );

    reg prev_done;

    always @(posedge clk) begin    
        prev_done <= done;

        if (reset) begin
            result <= 0;
            finished <= 0;
            prev_done <= 0;
        end else begin 
            if (done && ~prev_done) begin
                finished <= 1;
                result <= in;
            end else begin
                finished <= 0;
            end
        end
    end

endmodule

mlp_v1/negative_test_v2/relu.v
module relu 
    (   
        input wire signed [15:0] in,
        output reg signed [15:0] out
    );

    always @* begin
        if (in < 0)
            out = 0;
        else
            out = in;
    end

endmodule

mlp_v1/v3_2/multiply_unit.v
module multiply_unit 
    (   
        input wire clk,
        input wire reset,
        input wire signed [15:0] op1,
        input wire signed [7:0] op2,
        input wire signed [7:0] bias,
        output reg signed [15:0] out
    );

    reg signed [15:0] product;
    reg signed [15:0] sum;

    always @(posedge clk) begin
        product = op1 * op2;

        if (reset) begin
            sum = 0 + product;
        end else begin
            sum = sum + product;
        end

        out = sum + bias;
    end
    
endmodule


// what to do in case of overflows???

mlp_v1/v3_2/bias_mem.v
module bias_mem
    (
        input wire clk,
        input wire reset,
        input wire[15:0] input_addr,
        output reg signed [7:0] bias_val
    );

    wire [5:0] bias_addr = input_addr[15:10];

    // 3 * 16 + 1 (maximum number of possible output neurons)
    reg signed [7:0] bias_mem[0:48];

    initial begin 
        bias_mem[0] = 2;
        bias_mem[1] = 2;
        bias_mem[2] = 2;
        bias_mem[3] = 2;

        bias_mem[16] = 2;
        bias_mem[17] = 2;
        bias_mem[18] = 2;
        bias_mem[19] = 2;

        bias_mem[32] = 2;
    end

    always @(posedge clk) begin
        if (reset) begin
            bias_val <= 0;
        end else begin
            bias_val <= bias_mem[bias_addr];
        end
    end

endmodule

mlp_v1/v3_2/weight_mem.v
module weight_mem
    (
        input wire clk, 
        input wire reset,
        input wire [15:0] input_addr,
        output reg signed [7:0] weight_val
    );

    // 2^16 (size of neuron address) requires 65536 addresses
    reg signed [7:0] weight_mem[0:65535];

    // initializing input layer
    initial begin
        // layer 1 neuron 0
        weight_mem[16'h0000] <= 2;
        weight_mem[16'h0001] <= 2;
        weight_mem[16'h0002] <= 2;
        weight_mem[16'h0003] <= 2;
        weight_mem[16'h0004] <= 2;
        weight_mem[16'h0005] <= 2;
        weight_mem[16'h0006] <= 2;
        weight_mem[16'h0007] <= 2;
        weight_mem[16'h0008] <= 2;
        weight_mem[16'h0009] <= 2;
        weight_mem[16'h000A] <= 2;
        weight_mem[16'h000B] <= 2;
        weight_mem[16'h000C] <= 2;
        weight_mem[16'h000D] <= 2;
        weight_mem[16'h000E] <= 2;
        weight_mem[16'h000F] <= 2;

        // layer 1 neuron 1
        weight_mem[16'h0400] <= 2;
        weight_mem[16'h0401] <= 2;
        weight_mem[16'h0402] <= 2;
        weight_mem[16'h0403] <= 2;
        weight_mem[16'h0404] <= 2;
        weight_mem[16'h0405] <= 2;
        weight_mem[16'h0406] <= 2;
        weight_mem[16'h0407] <= 2;
        weight_mem[16'h0408] <= 2;
        weight_mem[16'h0409] <= 2;
        weight_mem[16'h040A] <= 2;
        weight_mem[16'h040B] <= 2;
        weight_mem[16'h040C] <= 2;
        weight_mem[16'h040D] <= 2;
        weight_mem[16'h040E] <= 2;
        weight_mem[16'h040F] <= 2;

        // layer 1 neuron 2
        weight_mem[16'h0800] <= 2;
        weight_mem[16'h0801] <= 2;
        weight_mem[16'h0802] <= 2;
        weight_mem[16'h0803] <= 2;
        weight_mem[16'h0804] <= 2;
        weight_mem[16'h0805] <= 2;
        weight_mem[16'h0806] <= 2;
        weight_mem[16'h0807] <= 2;
        weight_mem[16'h0808] <= 2;
        weight_mem[16'h0809] <= 2;
        weight_mem[16'h080A] <= 2;
        weight_mem[16'h080B] <= 2;
        weight_mem[16'h080C] <= 2;
        weight_mem[16'h080D] <= 2;
        weight_mem[16'h080E] <= 2;
        weight_mem[16'h080F] <= 2;

        // layer 1 neuron 3
        weight_mem[16'h0C00] <= 2;
        weight_mem[16'h0C01] <= 2;
        weight_mem[16'h0C02] <= 2;
        weight_mem[16'h0C03] <= 2;
        weight_mem[16'h0C04] <= 2;
        weight_mem[16'h0C05] <= 2;
        weight_mem[16'h0C06] <= 2;
        weight_mem[16'h0C07] <= 2;
        weight_mem[16'h0C08] <= 2;
        weight_mem[16'h0C09] <= 2;
        weight_mem[16'h0C0A] <= 2;
        weight_mem[16'h0C0B] <= 2;
        weight_mem[16'h0C0C] <= 2;
        weight_mem[16'h0C0D] <= 2;
        weight_mem[16'h0C0E] <= 2;
        weight_mem[16'h0C0F] <= 2;

        // layer 2 neuron 0
        weight_mem[16'h4000] <= 2;
        weight_mem[16'h4001] <= 2;
        weight_mem[16'h4002] <= 2;
        weight_mem[16'h4003] <= 2;

        // layer 2 neuron 1
        weight_mem[16'h4400] <= 2;
        weight_mem[16'h4401] <= 2;
        weight_mem[16'h4402] <= 2;
        weight_mem[16'h4403] <= 2;

        // layer 2 neuron 2
        weight_mem[16'h4800] <= 2;
        weight_mem[16'h4801] <= 2;
        weight_mem[16'h4802] <= 2;
        weight_mem[16'h4803] <= 2;

        // layer 2 neuron 3
        weight_mem[16'h4C00] <= 2;
        weight_mem[16'h4C01] <= 2;
        weight_mem[16'h4C02] <= 2;
        weight_mem[16'h4C03] <= 2;

        // layer 3 neuron 0
        weight_mem[16'h8000] <= 2;
        weight_mem[16'h8001] <= 2;
        weight_mem[16'h8002] <= 2;
        weight_mem[16'h8003] <= 2;     
    end

    always @(posedge clk) begin
        if (reset) begin
            weight_val <= 0;
        end else begin 
            weight_val <= weight_mem[input_addr];
        end
    end

endmodule

mlp_v1/v3_2/neuron_mem.v
module neuron_mem
    (
        input wire clk, 
        input wire reset,
        input wire write_enable,
        input wire [11:0] input_addr,
        input wire signed [15:0] data,
        input wire [11:0] output_addr,
        output reg signed [15:0] neuron_val
    );

    // 2^12 (size of neuron address) requires 4096 addresses
    reg signed [15:0] neuron_mem[0:4095];

    // initializing input layer
    initial begin
        neuron_mem[0] <= 4;
        neuron_mem[1] <= 4;
        neuron_mem[2] <= 4;
        neuron_mem[3] <= 4;
        neuron_mem[4] <= 4;
        neuron_mem[5] <= 4;
        neuron_mem[6] <= 4;
        neuron_mem[7] <= 4;
        neuron_mem[8] <= -3;
        neuron_mem[9] <= -3;
        neuron_mem[10] <= -3;
        neuron_mem[11] <= -3;
        neuron_mem[12] <= -3;
        neuron_mem[13] <= -3;
        neuron_mem[14] <= -3;
        neuron_mem[15] <= -3;
        
    end

    always @(posedge clk) begin
        if (reset) begin
            neuron_val <= 0;
        end else begin 
            if (input_addr == output_addr && write_enable) begin
                neuron_val <= data;
            end else begin
                neuron_val <= neuron_mem[input_addr];
            end 

            if (write_enable) begin
                neuron_mem[output_addr] <= data;
            end
        end
    end

endmodule

mlp_v1/v3_2/control_unit.v
module control_unit 
    (   
        input clk, 
        input reset,
        output reg [11:0] input_neuron_addr,
        output reg [11:0] output_neuron_addr,
        // 16 bits
        output reg [15:0] input_weight_addr,
        output reg reset_mult_acc,
        output reg write_neuron,
        output reg done
    );

    //////// neuron count array ////////
    parameter layers = 4;    // number of layers including input/output
    reg [7:0] neuron_count_array [layers - 1 : 0];  

    //////// variables ////////
    reg [9:0]  weight_ptr;
    reg [3:0]  neuron_ptr;
    reg [1:0]  layer_ptr;
    

    always @(posedge clk) begin
        if (reset) begin 
            neuron_count_array[0] = 16;
            neuron_count_array[1] = 4;
            neuron_count_array[2] = 4;
            neuron_count_array[3] = 1;

            weight_ptr <= 0;
            neuron_ptr <= 0;
            layer_ptr <= 0;

            input_neuron_addr <= 0;
            output_neuron_addr <= 0;
            input_weight_addr <= 0;
            
            done <= 0;
            write_neuron <= 0;
            reset_mult_acc <= 1; 
        end else begin
            // Last weight for current neuron, move to the next neuron 
            if (weight_ptr == neuron_count_array[layer_ptr] - 1) begin
        
                // Last neuron in current layer, move to the next layer
                if ((neuron_ptr + 1) == neuron_count_array[(layer_ptr + 1)]) begin

                    // Finished MLP calculations, proceed to softmax
                    if (neuron_count_array[(layer_ptr + 1)] == 1) begin 
                        done <= 1;
                    end else begin 
                        done <= 0;
                        layer_ptr <= layer_ptr + 1;
                        neuron_ptr <= 0;
                    end
                end else begin 
                    neuron_ptr <= neuron_ptr + 1;
                end

                weight_ptr <= 0;
                write_neuron <= 1;
                reset_mult_acc <= 1; 
            end else begin
                weight_ptr <= weight_ptr + 1;
                write_neuron <= 0;
                reset_mult_acc <= 0;
            end

            // input neuron address = layer_ptr | weight_ptr, 12 bits 
            input_neuron_addr <= {layer_ptr, weight_ptr};

            // output neuron address = layer_ptr + 1| neuron_ptr, 12 bits
            output_neuron_addr <= {(layer_ptr + 2'b01), 6'b000000, neuron_ptr};

            // weight address = layer_ptr | neuron_ptr | weight_ptr, 16 bits
            input_weight_addr <= {layer_ptr, neuron_ptr, weight_ptr};
        end  
    end

endmodule

mlp_v1/v3_2/top.v
module top 
    (
        input clk, 
        input reset, 
        output wire signed [15:0] out,
        output wire finished
    );

    // Internal signals
    wire [11:0] neuron_addr;
    wire [15:0] weight_addr;
    wire [7:0] bias_addr;

    wire [11:0] out_neuron_addr_1;
    wire [11:0] out_neuron_addr_2;
    wire [11:0] out_neuron_addr_3;

    wire reset_mu_1;
    wire reset_mu_2;
    wire reset_mu_3;

    wire write_neuron_1;
    wire write_neuron_2;
    wire write_neuron_3;

    wire done_1;
    wire done_2;
    wire done_3;

    wire [15:0] neuron_val;
    wire [7:0] weight_val;
    wire [7:0] bias_val;

    wire [15:0] mu_out;
    wire [15:0] ru_out;

    control_unit cu (
        .clk(clk),
        .reset(reset),
        .input_neuron_addr(neuron_addr),
        .output_neuron_addr(out_neuron_addr_1),
        .input_weight_addr(weight_addr),
        .reset_mult_acc(reset_mu_1),
        .write_neuron(write_neuron_1),
        .done(done_1)
    );

    neuron_mem nm (
        .clk(clk),
        .reset(reset),
        .write_enable(write_neuron_3),
        .input_addr(neuron_addr),
        .data(ru_out),
        .output_addr(out_neuron_addr_3),
        .neuron_val(neuron_val)
    );

    weight_mem wm (
        .clk(clk),
        .reset(reset),
        .input_addr(weight_addr),
        .weight_val(weight_val)
    );

    bias_mem bm (
        .clk(clk),
        .reset(reset),
        .input_addr(weight_addr),
        .bias_val(bias_val)
    );

    multiply_unit mu (   
        .clk(clk),
        .reset(reset_mu_3 || reset),
        .op1(neuron_val),
        .op2(weight_val),
        .bias(bias_val),
        .out(mu_out)
    );

    relu ru(
        .in(mu_out),
        .out(ru_out)
    );

    softmax su(
        .clk(clk), 
        .reset(reset),
        .done(done_3),
        .in(ru_out), 
        .finished(finished),
        .result(out)
    );

    buffer b1(
        .clk(clk), 
        .reset(reset),

        .reset_mu_in(reset_mu_1),
        .done_in(done_1),
        .write_neuron_in(write_neuron_1),
        .out_neuron_addr_in(out_neuron_addr_1),

        .reset_mu_out(reset_mu_2),
        .done_out(done_2),
        .write_neuron_out(write_neuron_2),
        .out_neuron_addr_out(out_neuron_addr_2)
    );

    buffer b2(
        .clk(clk), 
        .reset(reset),

        .reset_mu_in(reset_mu_2),
        .done_in(done_2),
        .write_neuron_in(write_neuron_2),
        .out_neuron_addr_in(out_neuron_addr_2),

        .reset_mu_out(reset_mu_3),
        .done_out(done_3),
        .write_neuron_out(write_neuron_3),
        .out_neuron_addr_out(out_neuron_addr_3)
    );

endmodule

mlp_v1/v3_2/top_tb.v
`timescale 1ns / 1ps

module top_tb;

    // Declare testbench signals
    reg clk;
    reg reset;
    wire [15:0] out;
    wire finished;

    // Instantiate the DUT (Device Under Test)
    top uut (
        .clk(clk),
        .reset(reset),
        .out(out),
        .finished(finished)
    );

    always #10 clk = ~clk; 

    initial begin
        clk = 1;
        reset = 1;

        #20
        reset = 0;
        
        // Wait and observe outputs
        #4000; 


        $finish;
    end

    initial begin
        $dumpfile("wave.vcd");  
        $dumpvars(0, uut);
    end

endmodule

mlp_v1/v3_2/wave.vcd
$date
	Fri Apr 11 14:47:41 2025
$end
$version
	Icarus Verilog
$end
$timescale
	1ps
$end
$scope module top_tb $end
$scope module uut $end
$var wire 1 ! clk $end
$var wire 1 " reset $end
$var wire 1 # write_neuron_3 $end
$var wire 1 $ write_neuron_2 $end
$var wire 1 % write_neuron_1 $end
$var wire 8 & weight_val [7:0] $end
$var wire 16 ' weight_addr [15:0] $end
$var wire 16 ( ru_out [15:0] $end
$var wire 1 ) reset_mu_3 $end
$var wire 1 * reset_mu_2 $end
$var wire 1 + reset_mu_1 $end
$var wire 12 , out_neuron_addr_3 [11:0] $end
$var wire 12 - out_neuron_addr_2 [11:0] $end
$var wire 12 . out_neuron_addr_1 [11:0] $end
$var wire 16 / out [15:0] $end
$var wire 16 0 neuron_val [15:0] $end
$var wire 12 1 neuron_addr [11:0] $end
$var wire 16 2 mu_out [15:0] $end
$var wire 1 3 finished $end
$var wire 1 4 done_3 $end
$var wire 1 5 done_2 $end
$var wire 1 6 done_1 $end
$var wire 8 7 bias_val [7:0] $end
$scope module b1 $end
$var wire 1 ! clk $end
$var wire 1 " reset $end
$var wire 1 % write_neuron_in $end
$var wire 1 + reset_mu_in $end
$var wire 12 8 out_neuron_addr_in [11:0] $end
$var wire 1 6 done_in $end
$var reg 1 5 done_out $end
$var reg 12 9 out_neuron_addr_out [11:0] $end
$var reg 1 * reset_mu_out $end
$var reg 1 $ write_neuron_out $end
$upscope $end
$scope module b2 $end
$var wire 1 ! clk $end
$var wire 1 5 done_in $end
$var wire 12 : out_neuron_addr_in [11:0] $end
$var wire 1 " reset $end
$var wire 1 * reset_mu_in $end
$var wire 1 $ write_neuron_in $end
$var reg 1 4 done_out $end
$var reg 12 ; out_neuron_addr_out [11:0] $end
$var reg 1 ) reset_mu_out $end
$var reg 1 # write_neuron_out $end
$upscope $end
$scope module bm $end
$var wire 1 ! clk $end
$var wire 1 " reset $end
$var wire 16 < input_addr [15:0] $end
$var wire 6 = bias_addr [5:0] $end
$var reg 8 > bias_val [7:0] $end
$upscope $end
$scope module cu $end
$var wire 1 ! clk $end
$var wire 1 " reset $end
$var parameter 32 ? layers $end
$var reg 1 6 done $end
$var reg 12 @ input_neuron_addr [11:0] $end
$var reg 16 A input_weight_addr [15:0] $end
$var reg 2 B layer_ptr [1:0] $end
$var reg 4 C neuron_ptr [3:0] $end
$var reg 12 D output_neuron_addr [11:0] $end
$var reg 1 + reset_mult_acc $end
$var reg 10 E weight_ptr [9:0] $end
$var reg 1 % write_neuron $end
$upscope $end
$scope module mu $end
$var wire 8 F bias [7:0] $end
$var wire 1 ! clk $end
$var wire 1 G reset $end
$var wire 8 H op2 [7:0] $end
$var wire 16 I op1 [15:0] $end
$var reg 16 J out [15:0] $end
$var reg 16 K product [15:0] $end
$var reg 16 L sum [15:0] $end
$upscope $end
$scope module nm $end
$var wire 1 ! clk $end
$var wire 12 M input_addr [11:0] $end
$var wire 12 N output_addr [11:0] $end
$var wire 1 " reset $end
$var wire 1 # write_enable $end
$var wire 16 O data [15:0] $end
$var reg 16 P neuron_val [15:0] $end
$upscope $end
$scope module ru $end
$var wire 16 Q in [15:0] $end
$var reg 16 R out [15:0] $end
$upscope $end
$scope module su $end
$var wire 1 ! clk $end
$var wire 1 4 done $end
$var wire 16 S in [15:0] $end
$var wire 1 " reset $end
$var reg 1 3 finished $end
$var reg 1 T prev_done $end
$var reg 16 U result [15:0] $end
$upscope $end
$scope module wm $end
$var wire 1 ! clk $end
$var wire 16 V input_addr [15:0] $end
$var wire 1 " reset $end
$var reg 8 W weight_val [7:0] $end
$upscope $end
$upscope $end
$upscope $end
$enddefinitions $end
$comment Show the parameter values. $end
$dumpall
b100 ?
$end
#0
$dumpvars
b0 W
b0 V
b0 U
0T
bx S
bx R
bx Q
b0 P
bx O
b0 N
b0 M
bx L
bx K
bx J
b0 I
b0 H
1G
b0 F
b0 E
b0 D
b0 C
b0 B
b0 A
b0 @
b0 >
b0 =
b0 <
b0 ;
b0 :
b0 9
b0 8
b0 7
06
05
04
03
bx 2
b0 1
b0 0
b0 /
b0 .
b0 -
b0 ,
1+
0*
0)
bx (
b0 '
b0 &
0%
0$
0#
1"
1!
$end
#10000
0!
#20000
1*
b10 7
b10 >
b10 F
b10 &
b10 H
b10 W
b100 0
b100 I
b100 P
b10000000000 .
b10000000000 8
b10000000000 D
0+
b1 E
b0 K
0G
1!
0"
#30000
0!
#40000
1G
b1 '
b1 <
b1 A
b1 V
b1 1
b1 @
b1 M
b10 E
b10000000000 -
b10000000000 9
b10000000000 :
0*
1)
b1000 K
1!
#50000
0!
#60000
0G
b10000000000 ,
b10000000000 ;
b10000000000 N
0)
b10 '
b10 <
b10 A
b10 V
b10 1
b10 @
b10 M
b11 E
b1010 (
b1010 O
b1010 R
b1010 S
b1010 2
b1010 J
b1010 Q
b1000 L
1!
#70000
0!
#80000
b11 '
b11 <
b11 A
b11 V
b11 1
b11 @
b11 M
b100 E
b10010 (
b10010 O
b10010 R
b10010 S
b10010 2
b10010 J
b10010 Q
b10000 L
1!
#90000
0!
#100000
b100 '
b100 <
b100 A
b100 V
b100 1
b100 @
b100 M
b101 E
b11010 (
b11010 O
b11010 R
b11010 S
b11010 2
b11010 J
b11010 Q
b11000 L
1!
#110000
0!
#120000
b101 '
b101 <
b101 A
b101 V
b101 1
b101 @
b101 M
b110 E
b100010 (
b100010 O
b100010 R
b100010 S
b100010 2
b100010 J
b100010 Q
b100000 L
1!
#130000
0!
#140000
b110 '
b110 <
b110 A
b110 V
b110 1
b110 @
b110 M
b111 E
b101010 (
b101010 O
b101010 R
b101010 S
b101010 2
b101010 J
b101010 Q
b101000 L
1!
#150000
0!
#160000
b111 '
b111 <
b111 A
b111 V
b111 1
b111 @
b111 M
b1000 E
b110010 (
b110010 O
b110010 R
b110010 S
b110010 2
b110010 J
b110010 Q
b110000 L
1!
#170000
0!
#180000
b1000 '
b1000 <
b1000 A
b1000 V
b1000 1
b1000 @
b1000 M
b1001 E
b111010 (
b111010 O
b111010 R
b111010 S
b111010 2
b111010 J
b111010 Q
b111000 L
1!
#190000
0!
#200000
b1001 '
b1001 <
b1001 A
b1001 V
b1001 1
b1001 @
b1001 M
b1010 E
b1111111111111101 0
b1111111111111101 I
b1111111111111101 P
b1000010 (
b1000010 O
b1000010 R
b1000010 S
b1000010 2
b1000010 J
b1000010 Q
b1000000 L
1!
#210000
0!
#220000
b1010 '
b1010 <
b1010 A
b1010 V
b1010 1
b1010 @
b1010 M
b1011 E
b111100 (
b111100 O
b111100 R
b111100 S
b111100 2
b111100 J
b111100 Q
b111010 L
b1111111111111010 K
1!
#230000
0!
#240000
b1011 '
b1011 <
b1011 A
b1011 V
b1011 1
b1011 @
b1011 M
b1100 E
b110110 (
b110110 O
b110110 R
b110110 S
b110110 2
b110110 J
b110110 Q
b110100 L
1!
#250000
0!
#260000
b1100 '
b1100 <
b1100 A
b1100 V
b1100 1
b1100 @
b1100 M
b1101 E
b110000 (
b110000 O
b110000 R
b110000 S
b110000 2
b110000 J
b110000 Q
b101110 L
1!
#270000
0!
#280000
b1101 '
b1101 <
b1101 A
b1101 V
b1101 1
b1101 @
b1101 M
b1110 E
b101010 (
b101010 O
b101010 R
b101010 S
b101010 2
b101010 J
b101010 Q
b101000 L
1!
#290000
0!
#300000
b1110 '
b1110 <
b1110 A
b1110 V
b1110 1
b1110 @
b1110 M
b1111 E
b100100 (
b100100 O
b100100 R
b100100 S
b100100 2
b100100 J
b100100 Q
b100010 L
1!
#310000
0!
#320000
b1111 '
b1111 <
b1111 A
b1111 V
b1111 1
b1111 @
b1111 M
1+
1%
b0 E
b1 C
b11110 (
b11110 O
b11110 R
b11110 S
b11110 2
b11110 J
b11110 Q
b11100 L
1!
#330000
0!
#340000
b1 =
1$
1*
b10000000000 '
b10000000000 <
b10000000000 A
b10000000000 V
b10000000001 .
b10000000001 8
b10000000001 D
b0 1
b0 @
b0 M
0+
0%
b1 E
b11000 (
b11000 O
b11000 R
b11000 S
b11000 2
b11000 J
b11000 Q
b10110 L
1!
#350000
0!
#360000
1G
b10000000001 '
b10000000001 <
b10000000001 A
b10000000001 V
b1 1
b1 @
b1 M
b10 E
b100 0
b100 I
b100 P
b10000000001 -
b10000000001 9
b10000000001 :
0$
0*
1#
1)
b10010 (
b10010 O
b10010 R
b10010 S
b10010 2
b10010 J
b10010 Q
b10000 L
1!
#370000
0!
#380000
0G
b10000000001 ,
b10000000001 ;
b10000000001 N
0#
0)
b10000000010 '
b10000000010 <
b10000000010 A
b10000000010 V
b10 1
b10 @
b10 M
b11 E
b1010 (
b1010 O
b1010 R
b1010 S
b1010 2
b1010 J
b1010 Q
b1000 L
b1000 K
1!
#390000
0!
#400000
b10000000011 '
b10000000011 <
b10000000011 A
b10000000011 V
b11 1
b11 @
b11 M
b100 E
b10010 (
b10010 O
b10010 R
b10010 S
b10010 2
b10010 J
b10010 Q
b10000 L
1!
#410000
0!
#420000
b10000000100 '
b10000000100 <
b10000000100 A
b10000000100 V
b100 1
b100 @
b100 M
b101 E
b11010 (
b11010 O
b11010 R
b11010 S
b11010 2
b11010 J
b11010 Q
b11000 L
1!
#430000
0!
#440000
b10000000101 '
b10000000101 <
b10000000101 A
b10000000101 V
b101 1
b101 @
b101 M
b110 E
b100010 (
b100010 O
b100010 R
b100010 S
b100010 2
b100010 J
b100010 Q
b100000 L
1!
#450000
0!
#460000
b10000000110 '
b10000000110 <
b10000000110 A
b10000000110 V
b110 1
b110 @
b110 M
b111 E
b101010 (
b101010 O
b101010 R
b101010 S
b101010 2
b101010 J
b101010 Q
b101000 L
1!
#470000
0!
#480000
b10000000111 '
b10000000111 <
b10000000111 A
b10000000111 V
b111 1
b111 @
b111 M
b1000 E
b110010 (
b110010 O
b110010 R
b110010 S
b110010 2
b110010 J
b110010 Q
b110000 L
1!
#490000
0!
#500000
b10000001000 '
b10000001000 <
b10000001000 A
b10000001000 V
b1000 1
b1000 @
b1000 M
b1001 E
b111010 (
b111010 O
b111010 R
b111010 S
b111010 2
b111010 J
b111010 Q
b111000 L
1!
#510000
0!
#520000
b10000001001 '
b10000001001 <
b10000001001 A
b10000001001 V
b1001 1
b1001 @
b1001 M
b1010 E
b1111111111111101 0
b1111111111111101 I
b1111111111111101 P
b1000010 (
b1000010 O
b1000010 R
b1000010 S
b1000010 2
b1000010 J
b1000010 Q
b1000000 L
1!
#530000
0!
#540000
b10000001010 '
b10000001010 <
b10000001010 A
b10000001010 V
b1010 1
b1010 @
b1010 M
b1011 E
b111100 (
b111100 O
b111100 R
b111100 S
b111100 2
b111100 J
b111100 Q
b111010 L
b1111111111111010 K
1!
#550000
0!
#560000
b10000001011 '
b10000001011 <
b10000001011 A
b10000001011 V
b1011 1
b1011 @
b1011 M
b1100 E
b110110 (
b110110 O
b110110 R
b110110 S
b110110 2
b110110 J
b110110 Q
b110100 L
1!
#570000
0!
#580000
b10000001100 '
b10000001100 <
b10000001100 A
b10000001100 V
b1100 1
b1100 @
b1100 M
b1101 E
b110000 (
b110000 O
b110000 R
b110000 S
b110000 2
b110000 J
b110000 Q
b101110 L
1!
#590000
0!
#600000
b10000001101 '
b10000001101 <
b10000001101 A
b10000001101 V
b1101 1
b1101 @
b1101 M
b1110 E
b101010 (
b101010 O
b101010 R
b101010 S
b101010 2
b101010 J
b101010 Q
b101000 L
1!
#610000
0!
#620000
b10000001110 '
b10000001110 <
b10000001110 A
b10000001110 V
b1110 1
b1110 @
b1110 M
b1111 E
b100100 (
b100100 O
b100100 R
b100100 S
b100100 2
b100100 J
b100100 Q
b100010 L
1!
#630000
0!
#640000
b10000001111 '
b10000001111 <
b10000001111 A
b10000001111 V
b1111 1
b1111 @
b1111 M
1+
1%
b0 E
b10 C
b11110 (
b11110 O
b11110 R
b11110 S
b11110 2
b11110 J
b11110 Q
b11100 L
1!
#650000
0!
#660000
b10 =
1$
1*
b100000000000 '
b100000000000 <
b100000000000 A
b100000000000 V
b10000000010 .
b10000000010 8
b10000000010 D
b0 1
b0 @
b0 M
0+
0%
b1 E
b11000 (
b11000 O
b11000 R
b11000 S
b11000 2
b11000 J
b11000 Q
b10110 L
1!
#670000
0!
#680000
1G
b100000000001 '
b100000000001 <
b100000000001 A
b100000000001 V
b1 1
b1 @
b1 M
b10 E
b100 0
b100 I
b100 P
b10000000010 -
b10000000010 9
b10000000010 :
0$
0*
1#
1)
b10010 (
b10010 O
b10010 R
b10010 S
b10010 2
b10010 J
b10010 Q
b10000 L
1!
#690000
0!
#700000
0G
b10000000010 ,
b10000000010 ;
b10000000010 N
0#
0)
b100000000010 '
b100000000010 <
b100000000010 A
b100000000010 V
b10 1
b10 @
b10 M
b11 E
b1010 (
b1010 O
b1010 R
b1010 S
b1010 2
b1010 J
b1010 Q
b1000 L
b1000 K
1!
#710000
0!
#720000
b100000000011 '
b100000000011 <
b100000000011 A
b100000000011 V
b11 1
b11 @
b11 M
b100 E
b10010 (
b10010 O
b10010 R
b10010 S
b10010 2
b10010 J
b10010 Q
b10000 L
1!
#730000
0!
#740000
b100000000100 '
b100000000100 <
b100000000100 A
b100000000100 V
b100 1
b100 @
b100 M
b101 E
b11010 (
b11010 O
b11010 R
b11010 S
b11010 2
b11010 J
b11010 Q
b11000 L
1!
#750000
0!
#760000
b100000000101 '
b100000000101 <
b100000000101 A
b100000000101 V
b101 1
b101 @
b101 M
b110 E
b100010 (
b100010 O
b100010 R
b100010 S
b100010 2
b100010 J
b100010 Q
b100000 L
1!
#770000
0!
#780000
b100000000110 '
b100000000110 <
b100000000110 A
b100000000110 V
b110 1
b110 @
b110 M
b111 E
b101010 (
b101010 O
b101010 R
b101010 S
b101010 2
b101010 J
b101010 Q
b101000 L
1!
#790000
0!
#800000
b100000000111 '
b100000000111 <
b100000000111 A
b100000000111 V
b111 1
b111 @
b111 M
b1000 E
b110010 (
b110010 O
b110010 R
b110010 S
b110010 2
b110010 J
b110010 Q
b110000 L
1!
#810000
0!
#820000
b100000001000 '
b100000001000 <
b100000001000 A
b100000001000 V
b1000 1
b1000 @
b1000 M
b1001 E
b111010 (
b111010 O
b111010 R
b111010 S
b111010 2
b111010 J
b111010 Q
b111000 L
1!
#830000
0!
#840000
b100000001001 '
b100000001001 <
b100000001001 A
b100000001001 V
b1001 1
b1001 @
b1001 M
b1010 E
b1111111111111101 0
b1111111111111101 I
b1111111111111101 P
b1000010 (
b1000010 O
b1000010 R
b1000010 S
b1000010 2
b1000010 J
b1000010 Q
b1000000 L
1!
#850000
0!
#860000
b100000001010 '
b100000001010 <
b100000001010 A
b100000001010 V
b1010 1
b1010 @
b1010 M
b1011 E
b111100 (
b111100 O
b111100 R
b111100 S
b111100 2
b111100 J
b111100 Q
b111010 L
b1111111111111010 K
1!
#870000
0!
#880000
b100000001011 '
b100000001011 <
b100000001011 A
b100000001011 V
b1011 1
b1011 @
b1011 M
b1100 E
b110110 (
b110110 O
b110110 R
b110110 S
b110110 2
b110110 J
b110110 Q
b110100 L
1!
#890000
0!
#900000
b100000001100 '
b100000001100 <
b100000001100 A
b100000001100 V
b1100 1
b1100 @
b1100 M
b1101 E
b110000 (
b110000 O
b110000 R
b110000 S
b110000 2
b110000 J
b110000 Q
b101110 L
1!
#910000
0!
#920000
b100000001101 '
b100000001101 <
b100000001101 A
b100000001101 V
b1101 1
b1101 @
b1101 M
b1110 E
b101010 (
b101010 O
b101010 R
b101010 S
b101010 2
b101010 J
b101010 Q
b101000 L
1!
#930000
0!
#940000
b100000001110 '
b100000001110 <
b100000001110 A
b100000001110 V
b1110 1
b1110 @
b1110 M
b1111 E
b100100 (
b100100 O
b100100 R
b100100 S
b100100 2
b100100 J
b100100 Q
b100010 L
1!
#950000
0!
#960000
b100000001111 '
b100000001111 <
b100000001111 A
b100000001111 V
b1111 1
b1111 @
b1111 M
1+
1%
b0 E
b11 C
b11110 (
b11110 O
b11110 R
b11110 S
b11110 2
b11110 J
b11110 Q
b11100 L
1!
#970000
0!
#980000
b11 =
1$
1*
b110000000000 '
b110000000000 <
b110000000000 A
b110000000000 V
b10000000011 .
b10000000011 8
b10000000011 D
b0 1
b0 @
b0 M
0+
0%
b1 E
b11000 (
b11000 O
b11000 R
b11000 S
b11000 2
b11000 J
b11000 Q
b10110 L
1!
#990000
0!
#1000000
1G
b110000000001 '
b110000000001 <
b110000000001 A
b110000000001 V
b1 1
b1 @
b1 M
b10 E
b100 0
b100 I
b100 P
b10000000011 -
b10000000011 9
b10000000011 :
0$
0*
1#
1)
b10010 (
b10010 O
b10010 R
b10010 S
b10010 2
b10010 J
b10010 Q
b10000 L
1!
#1010000
0!
#1020000
0G
b10000000011 ,
b10000000011 ;
b10000000011 N
0#
0)
b110000000010 '
b110000000010 <
b110000000010 A
b110000000010 V
b10 1
b10 @
b10 M
b11 E
b1010 (
b1010 O
b1010 R
b1010 S
b1010 2
b1010 J
b1010 Q
b1000 L
b1000 K
1!
#1030000
0!
#1040000
b110000000011 '
b110000000011 <
b110000000011 A
b110000000011 V
b11 1
b11 @
b11 M
b100 E
b10010 (
b10010 O
b10010 R
b10010 S
b10010 2
b10010 J
b10010 Q
b10000 L
1!
