mlp_v1/buffer_3.v
module buffer_3 (   
        input clk, 
        input run,
        
        input done_3,
        input [15:0] out_3,
        input [11:0] out_neuron_addr_3,
        input write_neuron_3,

        output reg done_4,
        output reg [15:0] out_4,
        output reg [11:0] out_neuron_addr_4,
        output reg write_neuron_4
    );

    initial begin
        done_4 <= 0;
        out_4 <= 16'b0;
        out_neuron_addr_4 <= 12'b0;
        write_neuron_4 <= 0;
    end

    always @(posedge clk) begin
        if (!run) begin
            done_4 <= 0;
            out_4 <= 16'b0;
            out_neuron_addr_4 <= 12'b0;
            write_neuron_4 <= 0;
        end else begin
            done_4 <= done_3;
            out_4 <= out_3;
            out_neuron_addr_4 <= out_neuron_addr_3;
            write_neuron_4 <= write_neuron_3;
        end
    end

endmodule

mlp_v1/buffer_2.v
module buffer_2 (   
        input clk, 
        input run,
        
        input done_2,
        input [15:0] neuron_val_2,
        input [7:0] weight_val_2,
        input reset_mult_acc_2,
        input [11:0] out_neuron_addr_2,
        input write_neuron_2,

        output reg done_3,
        output reg [15:0] neuron_val_3,
        output reg [7:0] weight_val_3,
        output reg reset_mult_acc_3,
        output reg [11:0] out_neuron_addr_3,
        output reg write_neuron_3
    );

    initial begin
        done_3 <= 0;
        neuron_val_3 <= 16'b0;
        weight_val_3 <= 8'b0;
        reset_mult_acc_3 <= 0;
        out_neuron_addr_3 <= 12'b0;
        write_neuron_3 <= 0;
    end

    always @(posedge clk) begin
        if (!run) begin
            done_3 <= 0;
            neuron_val_3 <= 16'b0;
            weight_val_3 <= 8'b0;
            reset_mult_acc_3 <= 0;
            out_neuron_addr_3 <= 12'b0;
            write_neuron_3 <= 0;
        end else begin
            done_3 <= done_2;
            neuron_val_3 <= neuron_val_2;
            weight_val_3 <= weight_val_2;
            reset_mult_acc_3 <= reset_mult_acc_2;
            out_neuron_addr_3 <= out_neuron_addr_2;
            write_neuron_3 <= write_neuron_2;
        end
    end

endmodule

mlp_v1/buffer_1.v
module buffer_1 (   
        input clk, 
        input run,

        input done_1,
        input [11:0] neuron_addr_1,
        input [15:0] weight_addr_1,
        input reset_mult_acc_1,
        input [11:0] out_neuron_addr_1,
        input write_neuron_1,

        output reg done_2,
        output reg [11:0] neuron_addr_2,
        output reg [15:0] weight_addr_2,
        output reg reset_mult_acc_2,
        output reg [11:0] out_neuron_addr_2,
        output reg write_neuron_2
    );

    initial begin
        done_2 <= 0;
        neuron_addr_2 <= 0;
        weight_addr_2 <= 0;
        reset_mult_acc_2 <= 0;
        out_neuron_addr_2 <= 0;
        write_neuron_2 <= 0;
    end

    always @(posedge clk) begin
        if (!run) begin
            done_2 <= 0;
            neuron_addr_2 <= 0;
            weight_addr_2 <= 0;
            reset_mult_acc_2 <= 0;
            out_neuron_addr_2 <= 0;
            write_neuron_2 <= 0;
        end else begin 
            done_2 <= done_1;
            neuron_addr_2 <= neuron_addr_1;
            weight_addr_2 <= weight_addr_1;
            reset_mult_acc_2 <= reset_mult_acc_1;
            out_neuron_addr_2 <= out_neuron_addr_1;
            write_neuron_2 <= write_neuron_1;
        end
    end
    
endmodule

mlp_v1/softmax.v
module softmax(
    input clk, 
    input done,
    input [15:0] in, 
    output reg finished, 
    output reg [15:0] result
);

initial begin
    result <= 0;
end

always @(negedge clk) begin
    if (done) begin
        result = in;
        finished = 1;
    end

    if (finished) begin
        finished = 0;
    end 
end

endmodule

mlp_v1/negative_test_v2/relu.v
module relu 
    (   
        input wire signed [15:0] in,
        output reg signed [15:0] out
    );

    always @* begin
        if (in < 0)
            out = 0;
        else
            out = in;
    end

endmodule

mlp_v1/positive_test_v1/multiply_unit.v
module multiply_unit 
    (   
        input wire clk,
        input wire reset,
        input wire signed [15:0] op1,
        input wire signed [7:0] op2,
        output reg signed [15:0] out
    );

    reg [15:0] product;
    reg [15:0] sum;

    initial begin
        sum <= 0;
        product <= 0;
        out <= 0;
    end 

    always @(negedge clk) begin
        product = op1 * op2;

        if (reset) begin
            sum = 0 + product;
        end else begin
            sum = sum + product;
        end

        out = sum;
    end
    
endmodule


// what to do in case of overflows???

mlp_v1/weight_mem.v
module weight_mem
    (
        input wire clk, 
        input wire [15:0] input_addr,
        output reg signed [7:0] weight_val
    );

    // 2^16 (size of neuron address) requires 65536 addresses
    reg [7:0] weight_mem[0:65535];

    // initializing input layer
    initial begin
        // layer 0 neuron 0 
        weight_mem[16'h0000] <= 16'h06;
        weight_mem[16'h0001] <= 16'h03;
        weight_mem[16'h0002] <= 16'h0d;
        weight_mem[16'h0003] <= 16'h07;

        // layer 0 neuron 1
        weight_mem[16'h0400] <= 16'h09;
        weight_mem[16'h0401] <= 16'h04;
        weight_mem[16'h0402] <= 16'h04;
        weight_mem[16'h0403] <= 16'h03;

        // layer 1 neuron 0
        weight_mem[16'h4000] <= 16'h0e;
        weight_mem[16'h4001] <= 16'h03;

        // layer 1 neuron 1
        weight_mem[16'h4400] <= 16'h08;
        weight_mem[16'h4401] <= 16'h04;

        // layer 2 neuron 0
        weight_mem[16'h8000] <= 16'h02;
        weight_mem[16'h8001] <= 16'h03;

        weight_val <= 16'h00;        
    end

    always @(negedge clk) begin
        weight_val = weight_mem[input_addr];
    end

endmodule

mlp_v1/neuron_mem.v
module neuron_mem
    (
        input wire clk, 
        input wire write_enable,
        input wire [11:0] input_addr,
        input wire signed [15:0] data,
        input wire [11:0] output_addr,
        output reg signed [15:0] neuron_val
    );

    // 2^12 (size of neuron address) requires 4096 addresses
    reg [15:0] neuron_mem[0:4095];

    // initializing input layer
    initial begin
        neuron_val <=  16'h00;

        neuron_mem[0] <= 16'h07;
        neuron_mem[1] <= 16'h05;
        neuron_mem[2] <= 16'h09;
        neuron_mem[3] <= 16'h04;
    end

    always @(negedge clk) begin
        if (write_enable) begin
            neuron_mem[output_addr] = data;
        end

        neuron_val = neuron_mem[input_addr];
    end

endmodule

mlp_v1/control_unit.v
module control_unit 
    (   
        input clk, 
        input run,
        output reg [11:0] input_neuron_addr,
        output reg [11:0] output_neuron_addr,
        // 16 bits
        output reg [15:0] input_weight_addr,
        output reg reset_mult_acc,
        output reg write_neuron,
        output reg done
    );



    //////// initialize outputs ////////
    initial begin
        reset_mult_acc = 0;            
        write_neuron = 0;              
        done = 0;  
        input_neuron_addr = 0;
        output_neuron_addr = 0;
        input_weight_addr = 0;
    end
    ////////////////////////////////////


    //////// neuron count array ////////
    parameter layers = 4;    // number of layers including input/output
    reg [7:0] neuron_count_array [layers - 1 : 0];  

    // providing values to neuron count array
    initial begin
        neuron_count_array[0] = 8'h04;
        neuron_count_array[1] = 8'h02;
        neuron_count_array[2] = 8'h02;
        neuron_count_array[3] = 8'h01;
    end
    ///////////////////////////////////



    //////// variables ////////
    reg [9:0]  weight_ptr;
    reg [3:0]  neuron_ptr;
    reg [1:0]  layer_ptr;

    initial begin
        weight_ptr = 10'b0;
        neuron_ptr = 4'b0;
        layer_ptr = 2'b0;
    end
    ///////////////////////////


    always @(negedge clk) begin
        if (run) begin 

                  
            /////////////////////////////////////////////////////////////

            // Last weight for current neuron, move to the next neuron 
            if (weight_ptr == neuron_count_array[layer_ptr] - 1) begin
        
                // Last neuron in current layer, move to the next layer
                if ((neuron_ptr + 1) == neuron_count_array[(layer_ptr + 1)]) begin

                    // Finished MLP calculations, proceed to softmax
                    if (neuron_count_array[(layer_ptr + 1)] == 1) begin 
                        done = 1;
                    end else begin 
                        done = 0;
                        layer_ptr = layer_ptr + 1;
                        neuron_ptr = 0;
                    end
                end else begin 
                    neuron_ptr = neuron_ptr + 1;
                end

                weight_ptr = 0;
                write_neuron = 1;
                reset_mult_acc = 1; 
            end else begin
                weight_ptr = weight_ptr + 1;
                write_neuron = 0;
                reset_mult_acc = 0;
            end


            //////// Set addresses /////////////////////////////////////
            // (can be optimized with address bases)

            // input neuron address = layer_ptr | weight_ptr, 12 bits 
            input_neuron_addr = {layer_ptr, weight_ptr};

            // output neuron address = layer_ptr + 1| neuron_ptr, 12 bits
            output_neuron_addr = {(layer_ptr + 2'b01), 6'b000000, neuron_ptr};

            // weight address = layer_ptr | neuron_ptr | weight_ptr, 16 bits
            input_weight_addr = {layer_ptr, neuron_ptr, weight_ptr};   

        // if run is false, i.e. we are restarting
        end else begin
            weight_ptr <= 0;
            neuron_ptr <= 0;
            layer_ptr <= 0;

            input_neuron_addr <= 0;
            output_neuron_addr <= 0;
            input_weight_addr <= 0;
            
            done <= 0;
            write_neuron <= 0;
            reset_mult_acc <= 0; 
        end  
    end

endmodule

mlp_v1/top.v
module top 
    (
        input clk, 
        input run, 
        output wire signed [15:0] out,
        output wire finished
    );

    // Internal signals
    wire [11:0] neuron_addr_1;
    wire [11:0] neuron_addr_2;

    wire [15:0] weight_addr_1;
    wire [15:0] weight_addr_2;

    wire [11:0] out_neuron_addr_1;
    wire [11:0] out_neuron_addr_2;
    wire [11:0] out_neuron_addr_3;
    wire [11:0] out_neuron_addr_4;

    wire reset_mult_acc_1;
    wire reset_mult_acc_2;
    wire reset_mult_acc_3;

    wire write_neuron_1;
    wire write_neuron_2;
    wire write_neuron_3;
    wire write_neuron_4;

    wire done_1;
    wire done_2;
    wire done_3;
    wire done_4;
    
    wire [15:0] neuron_val_2;
    wire [15:0] neuron_val_3;
    wire [7:0] weight_val_2;
    wire [7:0] weight_val_3;

    wire [15:0] mult_out_3;
    wire [15:0] out_3;
    wire [15:0] out_4;

    control_unit cu (
        .clk(clk),
        .run(run),
        .input_neuron_addr(neuron_addr_1),
        .output_neuron_addr(out_neuron_addr_1),
        .input_weight_addr(weight_addr_1),
        .reset_mult_acc(reset_mult_acc_1),
        .write_neuron(write_neuron_1),
        .done(done_1)
    );

    neuron_mem nm (
        .clk(clk),
        .write_enable(reset_mult_acc_3),
        .input_addr(neuron_addr_2),
        .data(out_4),
        .output_addr(out_neuron_addr_4),
        .neuron_val(neuron_val_2)
    );

    weight_mem wm (
        .clk(clk),
        .input_addr(weight_addr_2),
        .weight_val(weight_val_2)
    );

    multiply_unit mu (   
        .clk(clk),
        .reset(reset_mult_acc_3),
        .op1(neuron_val_3),
        .op2(weight_val_3),
        .out(mult_out_3)
    );

    relu ru(
        .in(mult_out_3),
        .out(out_3)
    );

    softmax su(
        .clk(clk), 
        .done(done_3),
        .in(out_4), 
        .finished(finished),
        .result(out)
    );

    buffer_1 b1 (
        .clk(clk), 
        .run(run),
        
        .done_1(done_1),
        .neuron_addr_1(neuron_addr_1),
        .weight_addr_1(weight_addr_1),
        .reset_mult_acc_1(reset_mult_acc_1),
        .out_neuron_addr_1(out_neuron_addr_1),
        .write_neuron_1(write_neuron_1),

        .done_2(done_2),
        .neuron_addr_2(neuron_addr_2),
        .weight_addr_2(weight_addr_2),
        .reset_mult_acc_2(reset_mult_acc_2),
        .out_neuron_addr_2(out_neuron_addr_2),
        .write_neuron_2(write_neuron_2)
    );

    buffer_2 b2 (
        .clk(clk), 
        .run(run),
        
        .done_2(done_2),
        .neuron_val_2(neuron_val_2),
        .weight_val_2(weight_val_2),
        .reset_mult_acc_2(reset_mult_acc_2),
        .out_neuron_addr_2(out_neuron_addr_2),
        .write_neuron_2(write_neuron_2),

        .done_3(done_3),
        .neuron_val_3(neuron_val_3),
        .weight_val_3(weight_val_3),
        .reset_mult_acc_3(reset_mult_acc_3),
        .out_neuron_addr_3(out_neuron_addr_3),
        .write_neuron_3(write_neuron_3)
    );

    buffer_3 b3 (
        .clk(clk), 
        .run(run),
        
        .done_3(done_3),
        .out_3(out_3),
        .out_neuron_addr_3(out_neuron_addr_3),
        .write_neuron_3(write_neuron_3),

        .done_4(done_4),
        .out_4(out_4),
        .out_neuron_addr_4(out_neuron_addr_4),
        .write_neuron_4(write_neuron_4)
    );

endmodule

mlp_v1/top_tb.v
`timescale 1ns / 1ps

module top_tb;

    // Declare testbench signals
    reg clk;
    reg run;
    wire [15:0] out;
    wire finished;

    // Instantiate the DUT (Device Under Test)
    top uut (
        .clk(clk),
        .run(run),
        .out(out),
        .finished(finished)
    );

    always #10 clk = ~clk; 

    initial begin
        clk = 0;
        run = 0;

        #10
        run = 1;
        
        // Wait and observe outputs
        #400; 

        run = 0;

        #40;

        run = 1;

        #400;

        $finish;
    end

    initial begin
        $dumpfile("wave.vcd");  
        $dumpvars(0, uut);
    end

endmodule

mlp_v1/wave.vcd
$date
	Sun Apr  6 18:43:42 2025
$end
$version
	Icarus Verilog
$end
$timescale
	1ps
$end
$scope module top_tb $end
$scope module uut $end
$var wire 1 ! clk $end
$var wire 1 " run $end
$var wire 1 # write_neuron_4 $end
$var wire 1 $ write_neuron_3 $end
$var wire 1 % write_neuron_2 $end
$var wire 1 & write_neuron_1 $end
$var wire 8 ' weight_val_3 [7:0] $end
$var wire 8 ( weight_val_2 [7:0] $end
$var wire 16 ) weight_addr_2 [15:0] $end
$var wire 16 * weight_addr_1 [15:0] $end
$var wire 1 + reset_mult_acc_3 $end
$var wire 1 , reset_mult_acc_2 $end
$var wire 1 - reset_mult_acc_1 $end
$var wire 12 . out_neuron_addr_4 [11:0] $end
$var wire 12 / out_neuron_addr_3 [11:0] $end
$var wire 12 0 out_neuron_addr_2 [11:0] $end
$var wire 12 1 out_neuron_addr_1 [11:0] $end
$var wire 16 2 out_4 [15:0] $end
$var wire 16 3 out_3 [15:0] $end
$var wire 16 4 out [15:0] $end
$var wire 16 5 neuron_val_3 [15:0] $end
$var wire 16 6 neuron_val_2 [15:0] $end
$var wire 12 7 neuron_addr_2 [11:0] $end
$var wire 12 8 neuron_addr_1 [11:0] $end
$var wire 16 9 mult_out_3 [15:0] $end
$var wire 1 : finished $end
$var wire 1 ; done_4 $end
$var wire 1 < done_3 $end
$var wire 1 = done_2 $end
$var wire 1 > done_1 $end
$scope module b1 $end
$var wire 1 ! clk $end
$var wire 1 " run $end
$var wire 1 & write_neuron_1 $end
$var wire 16 ? weight_addr_1 [15:0] $end
$var wire 1 - reset_mult_acc_1 $end
$var wire 12 @ out_neuron_addr_1 [11:0] $end
$var wire 12 A neuron_addr_1 [11:0] $end
$var wire 1 > done_1 $end
$var reg 1 = done_2 $end
$var reg 12 B neuron_addr_2 [11:0] $end
$var reg 12 C out_neuron_addr_2 [11:0] $end
$var reg 1 , reset_mult_acc_2 $end
$var reg 16 D weight_addr_2 [15:0] $end
$var reg 1 % write_neuron_2 $end
$upscope $end
$scope module b2 $end
$var wire 1 ! clk $end
$var wire 1 = done_2 $end
$var wire 12 E out_neuron_addr_2 [11:0] $end
$var wire 1 , reset_mult_acc_2 $end
$var wire 1 " run $end
$var wire 1 % write_neuron_2 $end
$var wire 8 F weight_val_2 [7:0] $end
$var wire 16 G neuron_val_2 [15:0] $end
$var reg 1 < done_3 $end
$var reg 16 H neuron_val_3 [15:0] $end
$var reg 12 I out_neuron_addr_3 [11:0] $end
$var reg 1 + reset_mult_acc_3 $end
$var reg 8 J weight_val_3 [7:0] $end
$var reg 1 $ write_neuron_3 $end
$upscope $end
$scope module b3 $end
$var wire 1 ! clk $end
$var wire 1 < done_3 $end
$var wire 12 K out_neuron_addr_3 [11:0] $end
$var wire 1 " run $end
$var wire 1 $ write_neuron_3 $end
$var wire 16 L out_3 [15:0] $end
$var reg 1 ; done_4 $end
$var reg 16 M out_4 [15:0] $end
$var reg 12 N out_neuron_addr_4 [11:0] $end
$var reg 1 # write_neuron_4 $end
$upscope $end
$scope module cu $end
$var wire 1 ! clk $end
$var wire 1 " run $end
$var parameter 32 O layers $end
$var reg 1 > done $end
$var reg 12 P input_neuron_addr [11:0] $end
$var reg 16 Q input_weight_addr [15:0] $end
$var reg 2 R layer_ptr [1:0] $end
$var reg 4 S neuron_ptr [3:0] $end
$var reg 12 T output_neuron_addr [11:0] $end
$var reg 1 - reset_mult_acc $end
$var reg 10 U weight_ptr [9:0] $end
$var reg 1 & write_neuron $end
$upscope $end
$scope module mu $end
$var wire 1 ! clk $end
$var wire 16 V op1 [15:0] $end
$var wire 8 W op2 [7:0] $end
$var wire 1 + reset $end
$var reg 16 X out [15:0] $end
$var reg 16 Y product [15:0] $end
$var reg 16 Z sum [15:0] $end
$upscope $end
$scope module nm $end
$var wire 1 ! clk $end
$var wire 16 [ data [15:0] $end
$var wire 12 \ input_addr [11:0] $end
$var wire 12 ] output_addr [11:0] $end
$var wire 1 + write_enable $end
$var reg 16 ^ neuron_val [15:0] $end
$upscope $end
$scope module ru $end
$var wire 16 _ in [15:0] $end
$var reg 16 ` out [15:0] $end
$upscope $end
$scope module su $end
$var wire 1 ! clk $end
$var wire 1 < done $end
$var wire 16 a in [15:0] $end
$var reg 1 : finished $end
$var reg 16 b result [15:0] $end
$upscope $end
$scope module wm $end
$var wire 1 ! clk $end
$var wire 16 c input_addr [15:0] $end
$var reg 8 d weight_val [7:0] $end
$upscope $end
$upscope $end
$upscope $end
$enddefinitions $end
$comment Show the parameter values. $end
$dumpall
b100 O
$end
#0
$dumpvars
b0 d
b0 c
b0 b
b0 a
b0 `
b0 _
b0 ^
b0 ]
b0 \
b0 [
b0 Z
b0 Y
b0 X
b0 W
b0 V
b0 U
b0 T
b0 S
b0 R
b0 Q
b0 P
b0 N
b0 M
b0 L
b0 K
b0 J
b0 I
b0 H
b0 G
b0 F
b0 E
b0 D
b0 C
b0 B
b0 A
b0 @
b0 ?
0>
0=
0<
0;
x:
b0 9
b0 8
b0 7
b0 6
b0 5
b0 4
b0 3
b0 2
b0 1
b0 0
b0 /
b0 .
0-
0,
0+
b0 *
b0 )
b0 (
b0 '
0&
0%
0$
0#
0"
0!
$end
#10000
1"
1!
#20000
b110 (
b110 F
b110 d
b111 6
b111 G
b111 ^
b1 *
b1 ?
b1 Q
b10000000000 1
b10000000000 @
b10000000000 T
b1 8
b1 A
b1 P
b1 U
0!
#30000
b110 '
b110 J
b110 W
b111 5
b111 H
b111 V
b10000000000 0
b10000000000 C
b10000000000 E
b1 )
b1 D
b1 c
b1 7
b1 B
b1 \
1!
#40000
b101010 3
b101010 L
b101010 `
b10 *
b10 ?
b10 Q
b10 8
b10 A
b10 P
b10 U
b101 6
b101 G
b101 ^
b11 (
b11 F
b11 d
b101010 9
b101010 X
b101010 _
b101010 Z
b101010 Y
0!
#50000
b10 )
b10 D
b10 c
b10 7
b10 B
b10 \
b10000000000 /
b10000000000 I
b10000000000 K
b11 '
b11 J
b11 W
b101 5
b101 H
b101 V
b101010 2
b101010 M
b101010 [
b101010 a
1!
#60000
b111001 3
b111001 L
b111001 `
b111001 9
b111001 X
b111001 _
b111001 Z
b1111 Y
b1101 (
b1101 F
b1101 d
b1001 6
b1001 G
b1001 ^
b11 *
b11 ?
b11 Q
b11 8
b11 A
b11 P
b11 U
0!
#70000
b10000000000 .
b10000000000 N
b10000000000 ]
b111001 2
b111001 M
b111001 [
b111001 a
b1101 '
b1101 J
b1101 W
b1001 5
b1001 H
b1001 V
b11 )
b11 D
b11 c
b11 7
b11 B
b11 \
1!
#80000
b10101110 3
b10101110 L
b10101110 `
b10000000000 *
b10000000000 ?
b10000000000 Q
b10000000001 1
b10000000001 @
b10000000001 T
b0 8
b0 A
b0 P
1-
1&
b0 U
b1 S
b100 6
b100 G
b100 ^
b111 (
b111 F
b111 d
b10101110 9
b10101110 X
b10101110 _
b10101110 Z
b1110101 Y
0!
#90000
1%
b10000000001 0
b10000000001 C
b10000000001 E
1,
b10000000000 )
b10000000000 D
b10000000000 c
b0 7
b0 B
b0 \
b111 '
b111 J
b111 W
b100 5
b100 H
b100 V
b10101110 2
b10101110 M
b10101110 [
b10101110 a
1!
#100000
b11001010 3
b11001010 L
b11001010 `
b11001010 9
b11001010 X
b11001010 _
b11001010 Z
b11100 Y
b1001 (
b1001 F
b1001 d
b111 6
b111 G
b111 ^
b10000000001 *
b10000000001 ?
b10000000001 Q
b1 8
b1 A
b1 P
0-
0&
b1 U
0!
#110000
b11001010 2
b11001010 M
b11001010 [
b11001010 a
1$
b10000000001 /
b10000000001 I
b10000000001 K
1+
b1001 '
b1001 J
b1001 W
b111 5
b111 H
b111 V
0%
0,
b10000000001 )
b10000000001 D
b10000000001 c
b1 7
b1 B
b1 \
1!
#120000
b111111 3
b111111 L
b111111 `
b10000000010 *
b10000000010 ?
b10000000010 Q
b10 8
b10 A
b10 P
b10 U
b101 6
b101 G
b101 ^
b100 (
b100 F
b100 d
b111111 9
b111111 X
b111111 _
b111111 Z
b111111 Y
0!
#130000
b10000000010 )
b10000000010 D
b10000000010 c
b10 7
b10 B
b10 \
0$
0+
b100 '
b100 J
b100 W
b101 5
b101 H
b101 V
1#
b10000000001 .
b10000000001 N
b10000000001 ]
b111111 2
b111111 M
b111111 [
b111111 a
1!
#140000
b1010011 3
b1010011 L
b1010011 `
b1010011 9
b1010011 X
b1010011 _
b1010011 Z
b10100 Y
b1001 6
b1001 G
b1001 ^
b10000000011 *
b10000000011 ?
b10000000011 Q
b11 8
b11 A
b11 P
b11 U
0!
#150000
0#
b1010011 2
b1010011 M
b1010011 [
b1010011 a
b1001 5
b1001 H
b1001 V
b10000000011 )
b10000000011 D
b10000000011 c
b11 7
b11 B
b11 \
1!
#160000
b1110111 3
b1110111 L
b1110111 `
b100000000000000 *
b100000000000000 ?
b100000000000000 Q
b100000000000 1
b100000000000 @
b100000000000 T
b10000000000 8
b10000000000 A
b10000000000 P
1-
1&
b0 U
b0 S
b1 R
b100 6
b100 G
b100 ^
b11 (
b11 F
b11 d
b1110111 9
b1110111 X
b1110111 _
b1110111 Z
b100100 Y
0!
#170000
1%
b100000000000 0
b100000000000 C
b100000000000 E
1,
b100000000000000 )
b100000000000000 D
b100000000000000 c
b10000000000 7
b10000000000 B
b10000000000 \
b11 '
b11 J
b11 W
b100 5
b100 H
b100 V
b1110111 2
b1110111 M
b1110111 [
b1110111 a
1!
#180000
b10000011 3
b10000011 L
b10000011 `
b10000011 9
b10000011 X
b10000011 _
b10000011 Z
b1100 Y
b1110 (
b1110 F
b1110 d
b11001010 6
b11001010 G
b11001010 ^
b100000000000001 *
b100000000000001 ?
b100000000000001 Q
b10000000001 8
b10000000001 A
b10000000001 P
0-
0&
b1 U
0!
#190000
b10000011 2
b10000011 M
b10000011 [
b10000011 a
1$
b100000000000 /
b100000000000 I
b100000000000 K
1+
b1110 '
b1110 J
b1110 W
b11001010 5
b11001010 H
b11001010 V
0%
0,
b100000000000001 )
b100000000000001 D
b100000000000001 c
b10000000001 7
b10000000001 B
b10000000001 \
1!
#200000
b101100001100 3
b101100001100 L
b101100001100 `
b100010000000000 *
b100010000000000 ?
b100010000000000 Q
b100000000001 1
b100000000001 @
b100000000001 T
b10000000000 8
b10000000000 A
b10000000000 P
1-
1&
b0 U
b1 S
b10000011 6
b10000011 G
b10000011 ^
b11 (
b11 F
b11 d
b101100001100 9
b101100001100 X
b101100001100 _
b101100001100 Z
b101100001100 Y
0!
#210000
1%
b100000000001 0
b100000000001 C
b100000000001 E
1,
b100010000000000 )
b100010000000000 D
b100010000000000 c
b10000000000 7
b10000000000 B
b10000000000 \
0$
0+
b11 '
b11 J
b11 W
b10000011 5
b10000011 H
b10000011 V
1#
b100000000000 .
b100000000000 N
b100000000000 ]
b101100001100 2
b101100001100 M
b101100001100 [
b101100001100 a
1!
#220000
b110010010101 3
b110010010101 L
b110010010101 `
b110010010101 9
b110010010101 X
b110010010101 _
b110010010101 Z
b110001001 Y
b1000 (
b1000 F
b1000 d
b11001010 6
b11001010 G
b11001010 ^
b100010000000001 *
b100010000000001 ?
b100010000000001 Q
b10000000001 8
b10000000001 A
b10000000001 P
0-
0&
b1 U
0!
#230000
0#
b110010010101 2
b110010010101 M
b110010010101 [
b110010010101 a
1$
b100000000001 /
b100000000001 I
b100000000001 K
1+
b1000 '
b1000 J
b1000 W
b11001010 5
b11001010 H
b11001010 V
0%
0,
b100010000000001 )
b100010000000001 D
b100010000000001 c
b10000000001 7
b10000000001 B
b10000000001 \
1!
#240000
b11001010000 3
b11001010000 L
b11001010000 `
b1000000000000000 *
b1000000000000000 ?
b1000000000000000 Q
b110000000000 1
b110000000000 @
b110000000000 T
b100000000000 8
b100000000000 A
b100000000000 P
1-
1&
b0 U
b0 S
b10 R
b10000011 6
b10000011 G
b10000011 ^
b100 (
b100 F
b100 d
b11001010000 9
b11001010000 X
b11001010000 _
b11001010000 Z
b11001010000 Y
0!
#250000
1%
b110000000000 0
b110000000000 C
b110000000000 E
1,
b1000000000000000 )
b1000000000000000 D
b1000000000000000 c
b100000000000 7
b100000000000 B
b100000000000 \
0$
0+
b100 '
b100 J
b100 W
b10000011 5
b10000011 H
b10000011 V
1#
b100000000001 .
b100000000001 N
b100000000001 ]
b11001010000 2
b11001010000 M
b11001010000 [
b11001010000 a
1!
#260000
b100001011100 3
b100001011100 L
b100001011100 `
b100001011100 9
b100001011100 X
b100001011100 _
b100001011100 Z
b1000001100 Y
b10 (
b10 F
b10 d
b110010010101 6
b110010010101 G
b110010010101 ^
b1000000000000001 *
b1000000000000001 ?
b1000000000000001 Q
b100000000001 8
b100000000001 A
b100000000001 P
0-
0&
b1 U
0!
#270000
0#
b100001011100 2
b100001011100 M
b100001011100 [
b100001011100 a
1$
b110000000000 /
b110000000000 I
b110000000000 K
1+
b10 '
b10 J
b10 W
b110010010101 5
b110010010101 H
b110010010101 V
0%
0,
b1000000000000001 )
b1000000000000001 D
b1000000000000001 c
b100000000001 7
b100000000001 B
b100000000001 \
1!
#280000
b1100100101010 3
b1100100101010 L
b1100100101010 `
b1000000000000000 *
b1000000000000000 ?
b1000000000000000 Q
b100000000000 8
b100000000000 A
b100000000000 P
1-
1&
b0 U
1>
b100001011100 6
b100001011100 G
b100001011100 ^
b11 (
b11 F
b11 d
b1100100101010 9
b1100100101010 X
b1100100101010 _
b1100100101010 Z
b1100100101010 Y
0!
#290000
1%
1,
b1000000000000000 )
b1000000000000000 D
b1000000000000000 c
b100000000000 7
b100000000000 B
b100000000000 \
1=
0$
0+
b11 '
b11 J
b11 W
b100001011100 5
b100001011100 H
b100001011100 V
1#
b110000000000 .
b110000000000 N
b110000000000 ]
b1100100101010 2
b1100100101010 M
b1100100101010 [
b1100100101010 a
1!
#300000
b11001000111110 3
b11001000111110 L
b11001000111110 `
b11001000111110 9
b11001000111110 X
b11001000111110 _
b11001000111110 Z
b1100100010100 Y
b10 (
b10 F
b10 d
b110010010101 6
b110010010101 G
b110010010101 ^
b1000000000000001 *
b1000000000000001 ?
b1000000000000001 Q
b100000000001 8
b100000000001 A
b100000000001 P
0-
0&
b1 U
0!
#310000
0#
b11001000111110 2
b11001000111110 M
b11001000111110 [
b11001000111110 a
1$
1+
b10 '
b10 J
b10 W
b110010010101 5
b110010010101 H
b110010010101 V
1<
0%
0,
b1000000000000001 )
b1000000000000001 D
b1000000000000001 c
b100000000001 7
b100000000001 B
b100000000001 \
1!
#320000
b1100100101010 3
b1100100101010 L
b1100100101010 `
b1000000000000000 *
b1000000000000000 ?
b1000000000000000 Q
b100000000000 8
b100000000000 A
b100000000000 P
1-
1&
b0 U
b100001011100 6
b100001011100 G
b100001011100 ^
b11 (
b11 F
b11 d
b1100100101010 9
b1100100101010 X
b1100100101010 _
b1100100101010 Z
b1100100101010 Y
0:
b11001000111110 4
b11001000111110 b
0!
#330000
1%
1,
b1000000000000000 )
b1000000000000000 D
b1000000000000000 c
b100000000000 7
b100000000000 B
b100000000000 \
0$
0+
b11 '
b11 J
b11 W
b100001011100 5
b100001011100 H
b100001011100 V
1#
b1100100101010 2
b1100100101010 M
b1100100101010 [
b1100100101010 a
1;
1!
#340000
b11001000111110 3
b11001000111110 L
b11001000111110 `
0:
b1100100101010 4
b1100100101010 b
b11001000111110 9
b11001000111110 X
b11001000111110 _
b11001000111110 Z
b1100100010100 Y
b10 (
b10 F
b10 d
b110010010101 6
b110010010101 G
b110010010101 ^
b1000000000000001 *
b1000000000000001 ?
b1000000000000001 Q
b100000000001 8
b100000000001 A
b100000000001 P
0-
0&
b1 U
0!
#350000
0#
b11001000111110 2
b11001000111110 M
b11001000111110 [
b11001000111110 a
1$
1+
b10 '
b10 J
b10 W
b110010010101 5
b110010010101 H
b110010010101 V
0%
0,
b1000000000000001 )
b1000000000000001 D
b1000000000000001 c
b100000000001 7
b100000000001 B
b100000000001 \
1!
#360000
b1100100101010 3
b1100100101010 L
b1100100101010 `
b1000000000000000 *
b1000000000000000 ?
b1000000000000000 Q
b100000000000 8
b100000000000 A
b100000000000 P
1-
1&
b0 U
b100001011100 6
b100001011100 G
b100001011100 ^
b11 (
b11 F
b11 d
b1100100101010 9
b1100100101010 X
b1100100101010 _
b1100100101010 Z
b1100100101010 Y
0:
b11001000111110 4
b11001000111110 b
0!
#370000
1%
1,
b1000000000000000 )
b1000000000000000 D
b1000000000000000 c
b100000000000 7
b100000000000 B
b100000000000 \
0$
0+
b11 '
b11 J
b11 W
b100001011100 5
b100001011100 H
b100001011100 V
1#
b1100100101010 2
b1100100101010 M
b1100100101010 [
b1100100101010 a
1!
#380000
b11001000111110 3
b11001000111110 L
b11001000111110 `
0:
b1100100101010 4
b1100100101010 b
b11001000111110 9
b11001000111110 X
b11001000111110 _
b11001000111110 Z
b1100100010100 Y
b10 (
b10 F
b10 d
b110010010101 6
b110010010101 G
b110010010101 ^
b1000000000000001 *
b1000000000000001 ?
b1000000000000001 Q
b100000000001 8
b100000000001 A
b100000000001 P
0-
0&
b1 U
0!
#390000
0#
b11001000111110 2
b11001000111110 M
b11001000111110 [
b11001000111110 a
1$
1+
b10 '
b10 J
b10 W
b110010010101 5
b110010010101 H
b110010010101 V
0%
0,
b1000000000000001 )
b1000000000000001 D
b1000000000000001 c
b100000000001 7
b100000000001 B
b100000000001 \
1!
